[{
		"name":	"Volume",
		"row_count":	1,
		"rows":	[{
				"GUID:s":	"0D8AD40D_281E6001",
				"DoesCameraColl:d":	1,
				"DoesCameraFade:d":	1,
				"LightChannels:d":	1,
				"ObjectFlags:d":	432,
				"ScriptResource:s":	"",
				"InitialPos:fff":	[-7009.8447265625, -1981.2066650390625, -15397.2177734375],
				"Orientation:fff":	[0, 0, 0],
				"LocalBoundingBox:ffffff":	[-50, -50, -50, 50, 50, 50],
				"ObjSaveFlag:d":	0,
				"ObjName:s":	"Balin SnapTo",
				"Name:s":	"Balin SnapTo",
				"Pos:fff":	[-7009.8447265625, -1981.2066650390625, -15397.2177734375],
				"BBox:ffffff":	[-7059.8447265625, -2031.2066650390625, -15447.2177734375, -6959.8447265625, -1931.2066650390625, -15347.2177734375],
				"Orient:fff":	[0, 0, 0],
				"HalfDimensions:fff":	[50, 50, 50],
				"Pain:s":	"none"
			}]
	}, {
		"name":	"Volume",
		"row_count":	1,
		"rows":	[{
				"GUID:s":	"0D8ADD0B_46F4E400",
				"DoesCameraColl:d":	1,
				"DoesCameraFade:d":	1,
				"LightChannels:d":	1,
				"ObjectFlags:d":	432,
				"ScriptResource:s":	"",
				"InitialPos:fff":	[-5961.37060546875, -1166.189208984375, -13108.0859375],
				"Orientation:fff":	[0, 0, 0],
				"LocalBoundingBox:ffffff":	[-122.62538146972656, -302.02328491210937, -367.76028442382812, 122.62538146972656, 302.02328491210937, 367.76028442382812],
				"ObjSaveFlag:d":	0,
				"ObjName:s":	"Bat10_Alert_Vol",
				"Name:s":	"Bat10_Alert_Vol",
				"Pos:fff":	[-5961.37060546875, -1166.189208984375, -13108.0859375],
				"BBox:ffffff":	[-6083.99609375, -1468.2125244140625, -13475.8466796875, -5838.7451171875, -864.1658935546875, -12740.3251953125],
				"Orient:fff":	[0, 0, 0],
				"HalfDimensions:fff":	[122.62538146972656, 302.02328491210937, 367.76028442382812],
				"Pain:s":	"none"
			}]
	}, {
		"name":	"Volume",
		"row_count":	1,
		"rows":	[{
				"GUID:s":	"0D8ADD0B_46F22800",
				"DoesCameraColl:d":	1,
				"DoesCameraFade:d":	1,
				"LightChannels:d":	1,
				"ObjectFlags:d":	432,
				"ScriptResource:s":	"",
				"InitialPos:fff":	[-6465.8564453125, 971.8583984375, -11092.1298828125],
				"Orientation:fff":	[0, 0, 0],
				"LocalBoundingBox:ffffff":	[-0.5, -0.5, -0.5, 0.5, 0.5, 0.5],
				"ObjSaveFlag:d":	0,
				"ObjName:s":	"Bat10_Run_Vol 001",
				"Name:s":	"Bat10_Run_Vol 001",
				"Pos:fff":	[-6465.8564453125, 971.8583984375, -11092.1298828125],
				"BBox:ffffff":	[-6466.3564453125, 971.3583984375, -11092.6298828125, -6465.3564453125, 972.3583984375, -11091.6298828125],
				"Orient:fff":	[0, 0, 0],
				"HalfDimensions:fff":	[0.5, 0.5, 0.5],
				"Pain:s":	"none"
			}]
	}, {
		"name":	"Volume",
		"row_count":	1,
		"rows":	[{
				"GUID:s":	"0D8ADD0B_46F2E001",
				"DoesCameraColl:d":	1,
				"DoesCameraFade:d":	1,
				"LightChannels:d":	1,
				"ObjectFlags:d":	432,
				"ScriptResource:s":	"",
				"InitialPos:fff":	[-6125.11083984375, 778.94073486328125, -11847.193359375],
				"Orientation:fff":	[0, 0, 0],
				"LocalBoundingBox:ffffff":	[-0.5, -0.5, -0.5, 0.5, 0.5, 0.5],
				"ObjSaveFlag:d":	0,
				"ObjName:s":	"Bat10_Run_Vol 002",
				"Name:s":	"Bat10_Run_Vol 002",
				"Pos:fff":	[-6125.11083984375, 778.94073486328125, -11847.193359375],
				"BBox:ffffff":	[-6125.61083984375, 778.44073486328125, -11847.693359375, -6124.61083984375, 779.44073486328125, -11846.693359375],
				"Orient:fff":	[0, 0, 0],
				"HalfDimensions:fff":	[0.5, 0.5, 0.5],
				"Pain:s":	"none"
			}]
	}, {
		"name":	"Volume",
		"row_count":	1,
		"rows":	[{
				"GUID:s":	"0D8ADD0B_46F3A001",
				"DoesCameraColl:d":	1,
				"DoesCameraFade:d":	1,
				"LightChannels:d":	1,
				"ObjectFlags:d":	432,
				"ScriptResource:s":	"",
				"InitialPos:fff":	[-6161.8037109375, 409.6220703125, -12574.9306640625],
				"Orientation:fff":	[0, 0, 0],
				"LocalBoundingBox:ffffff":	[-0.5, -0.5, -0.5, 0.5, 0.5, 0.5],
				"ObjSaveFlag:d":	0,
				"ObjName:s":	"Bat10_Run_Vol 003",
				"Name:s":	"Bat10_Run_Vol 003",
				"Pos:fff":	[-6161.8037109375, 409.6220703125, -12574.9306640625],
				"BBox:ffffff":	[-6162.3037109375, 409.1220703125, -12575.4306640625, -6161.3037109375, 410.1220703125, -12574.4306640625],
				"Orient:fff":	[0, 0, 0],
				"HalfDimensions:fff":	[0.5, 0.5, 0.5],
				"Pain:s":	"none"
			}]
	}, {
		"name":	"Volume",
		"row_count":	1,
		"rows":	[{
				"GUID:s":	"0D8ADD0B_46F42001",
				"DoesCameraColl:d":	1,
				"DoesCameraFade:d":	1,
				"LightChannels:d":	1,
				"ObjectFlags:d":	432,
				"ScriptResource:s":	"",
				"InitialPos:fff":	[-6161.8037109375, -466.5997314453125, -12574.9306640625],
				"Orientation:fff":	[0, 0, 0],
				"LocalBoundingBox:ffffff":	[-0.5, -0.5, -0.5, 0.5, 0.5, 0.5],
				"ObjSaveFlag:d":	0,
				"ObjName:s":	"Bat10_Run_Vol 004",
				"Name:s":	"Bat10_Run_Vol 004",
				"Pos:fff":	[-6161.8037109375, -466.5997314453125, -12574.9306640625],
				"BBox:ffffff":	[-6162.3037109375, -467.0997314453125, -12575.4306640625, -6161.3037109375, -466.0997314453125, -12574.4306640625],
				"Orient:fff":	[0, 0, 0],
				"HalfDimensions:fff":	[0.5, 0.5, 0.5],
				"Pain:s":	"none"
			}]
	}, {
		"name":	"Volume",
		"row_count":	1,
		"rows":	[{
				"GUID:s":	"0D8ADCCC_6E3AC801",
				"DoesCameraColl:d":	1,
				"DoesCameraFade:d":	1,
				"LightChannels:d":	1,
				"ObjectFlags:d":	432,
				"ScriptResource:s":	"",
				"InitialPos:fff":	[3734.763916015625, -558.49139404296875, -7159.91845703125],
				"Orientation:fff":	[0, 0, 0],
				"LocalBoundingBox:ffffff":	[-50, -50, -50, 50, 50, 50],
				"ObjSaveFlag:d":	0,
				"ObjName:s":	"Bat11 FaceVol",
				"Name:s":	"Bat11 FaceVol",
				"Pos:fff":	[3734.763916015625, -558.49139404296875, -7159.91845703125],
				"BBox:ffffff":	[3684.763916015625, -608.49139404296875, -7209.91845703125, 3784.763916015625, -508.49139404296875, -7109.91845703125],
				"Orient:fff":	[0, 0, 0],
				"HalfDimensions:fff":	[50, 50, 50],
				"Pain:s":	"none"
			}]
	}, {
		"name":	"Volume",
		"row_count":	1,
		"rows":	[{
				"GUID:s":	"0D8ADCCC_6E3C2001",
				"DoesCameraColl:d":	1,
				"DoesCameraFade:d":	1,
				"LightChannels:d":	1,
				"ObjectFlags:d":	432,
				"ScriptResource:s":	"",
				"InitialPos:fff":	[2695.172119140625, -751.11285400390625, -5748.49169921875],
				"Orientation:fff":	[0, 0, 0],
				"LocalBoundingBox:ffffff":	[-269.75128173828125, -173.59503173828125, -221.3399658203125, 269.75128173828125, 173.59503173828125, 221.3399658203125],
				"ObjSaveFlag:d":	0,
				"ObjName:s":	"Bat11 SpawnTrig",
				"Name:s":	"Bat11 SpawnTrig",
				"Pos:fff":	[2695.172119140625, -751.11285400390625, -5748.49169921875],
				"BBox:ffffff":	[2425.4208984375, -924.7078857421875, -5969.83154296875, 2964.92333984375, -577.517822265625, -5527.15185546875],
				"Orient:fff":	[0, 0, 0],
				"HalfDimensions:fff":	[269.75128173828125, 173.59503173828125, 221.3399658203125],
				"Pain:s":	"none"
			}]
	}, {
		"name":	"Volume",
		"row_count":	1,
		"rows":	[{
				"GUID:s":	"0D8ADCCC_6E39EC00",
				"DoesCameraColl:d":	1,
				"DoesCameraFade:d":	1,
				"LightChannels:d":	1,
				"ObjectFlags:d":	432,
				"ScriptResource:s":	"",
				"InitialPos:fff":	[3922.395263671875, -558.491455078125, -7159.91845703125],
				"Orientation:fff":	[0, 0, 0],
				"LocalBoundingBox:ffffff":	[-50, -50, -50, 50, 50, 50],
				"ObjSaveFlag:d":	0,
				"ObjName:s":	"Bat11 SpawnVol",
				"Name:s":	"Bat11 SpawnVol",
				"Pos:fff":	[3922.395263671875, -558.491455078125, -7159.91845703125],
				"BBox:ffffff":	[3872.395263671875, -608.491455078125, -7209.91845703125, 3972.395263671875, -508.491455078125, -7109.91845703125],
				"Orient:fff":	[0, 0, 0],
				"HalfDimensions:fff":	[50, 50, 50],
				"Pain:s":	"none"
			}]
	}, {
		"name":	"Volume",
		"row_count":	1,
		"rows":	[{
				"GUID:s":	"0D8AD14B_48D48C01",
				"DoesCameraColl:d":	1,
				"DoesCameraFade:d":	1,
				"LightChannels:d":	1,
				"ObjectFlags:d":	432,
				"ScriptResource:s":	"",
				"InitialPos:fff":	[3333.1171875, -807.0362548828125, -5981.31884765625],
				"Orientation:fff":	[0, 0, 0],
				"LocalBoundingBox:ffffff":	[-103.70829010009766, -130.91081237792969, -113.47728729248047, 103.70829010009766, 130.91081237792969, 113.47728729248047],
				"ObjSaveFlag:d":	0,
				"ObjName:s":	"Bat11_Alert Vol",
				"Name:s":	"Bat11_Alert Vol",
				"Pos:fff":	[3333.1171875, -807.0362548828125, -5981.31884765625],
				"BBox:ffffff":	[3229.408935546875, -937.94708251953125, -6094.7958984375, 3436.825439453125, -676.12542724609375, -5867.841796875],
				"Orient:fff":	[0, 0, 0],
				"HalfDimensions:fff":	[103.70829010009766, 130.91081237792969, 113.47728729248047],
				"Pain:s":	"none"
			}]
	}, {
		"name":	"Volume",
		"row_count":	1,
		"rows":	[{
				"GUID:s":	"0D8AD14B_48D38800",
				"DoesCameraColl:d":	1,
				"DoesCameraFade:d":	1,
				"LightChannels:d":	1,
				"ObjectFlags:d":	432,
				"ScriptResource:s":	"",
				"InitialPos:fff":	[3472.688232421875, -588.870849609375, -7158.34814453125],
				"Orientation:fff":	[0, 0, 0],
				"LocalBoundingBox:ffffff":	[-0.5, -78.3897171020508, -0.5, 0.5, 78.3897171020508, 0.5],
				"ObjSaveFlag:d":	0,
				"ObjName:s":	"Bat11_Run_Vol 001",
				"Name:s":	"Bat11_Run_Vol 001",
				"Pos:fff":	[3472.688232421875, -588.870849609375, -7158.34814453125],
				"BBox:ffffff":	[3472.188232421875, -667.26055908203125, -7158.84814453125, 3473.188232421875, -510.48114013671875, -7157.84814453125],
				"Orient:fff":	[0, 0, 0],
				"HalfDimensions:fff":	[0.5, 78.3897171020508, 0.5],
				"Pain:s":	"none"
			}]
	}, {
		"name":	"Volume",
		"row_count":	1,
		"rows":	[{
				"GUID:s":	"0D8AD14B_48D46001",
				"DoesCameraColl:d":	1,
				"DoesCameraFade:d":	1,
				"LightChannels:d":	1,
				"ObjectFlags:d":	432,
				"ScriptResource:s":	"",
				"InitialPos:fff":	[3472.688232421875, -588.870849609375, -6962.7744140625],
				"Orientation:fff":	[0, 0, 0],
				"LocalBoundingBox:ffffff":	[-0.5, -78.3897171020508, -0.5, 0.5, 78.3897171020508, 0.5],
				"ObjSaveFlag:d":	0,
				"ObjName:s":	"Bat11_Run_Vol 002",
				"Name:s":	"Bat11_Run_Vol 002",
				"Pos:fff":	[3472.688232421875, -588.870849609375, -6962.7744140625],
				"BBox:ffffff":	[3472.188232421875, -667.26055908203125, -6963.2744140625, 3473.188232421875, -510.48114013671875, -6962.2744140625],
				"Orient:fff":	[0, 0, 0],
				"HalfDimensions:fff":	[0.5, 78.3897171020508, 0.5],
				"Pain:s":	"none"
			}]
	}, {
		"name":	"Volume",
		"row_count":	1,
		"rows":	[{
				"GUID:s":	"0D8ADE8B_7B9B1401",
				"DoesCameraColl:d":	1,
				"DoesCameraFade:d":	1,
				"LightChannels:d":	1,
				"ObjectFlags:d":	432,
				"ScriptResource:s":	"",
				"InitialPos:fff":	[3445.574951171875, -588.870849609375, -6734.10009765625],
				"Orientation:fff":	[0, 0, 0],
				"LocalBoundingBox:ffffff":	[-0.5, -78.3897171020508, -0.5, 0.5, 78.3897171020508, 0.5],
				"ObjSaveFlag:d":	0,
				"ObjName:s":	"Bat11_Run_Vol 003",
				"Name:s":	"Bat11_Run_Vol 003",
				"Pos:fff":	[3445.574951171875, -588.870849609375, -6734.10009765625],
				"BBox:ffffff":	[3445.074951171875, -667.26055908203125, -6734.60009765625, 3446.074951171875, -510.48114013671875, -6733.60009765625],
				"Orient:fff":	[0, 0, 0],
				"HalfDimensions:fff":	[0.5, 78.3897171020508, 0.5],
				"Pain:s":	"none"
			}]
	}, {
		"name":	"Volume",
		"row_count":	1,
		"rows":	[{
				"GUID:s":	"0D8ADE8B_7B9B2401",
				"DoesCameraColl:d":	1,
				"DoesCameraFade:d":	1,
				"LightChannels:d":	1,
				"ObjectFlags:d":	432,
				"ScriptResource:s":	"",
				"InitialPos:fff":	[3398.73583984375, -588.870849609375, -6511.92529296875],
				"Orientation:fff":	[0, 0, 0],
				"LocalBoundingBox:ffffff":	[-0.5, -78.3897171020508, -0.5, 0.5, 78.3897171020508, 0.5],
				"ObjSaveFlag:d":	0,
				"ObjName:s":	"Bat11_Run_Vol 004",
				"Name:s":	"Bat11_Run_Vol 004",
				"Pos:fff":	[3398.73583984375, -588.870849609375, -6511.92529296875],
				"BBox:ffffff":	[3398.23583984375, -667.26055908203125, -6512.42529296875, 3399.23583984375, -510.48114013671875, -6511.42529296875],
				"Orient:fff":	[0, 0, 0],
				"HalfDimensions:fff":	[0.5, 78.3897171020508, 0.5],
				"Pain:s":	"none"
			}]
	}, {
		"name":	"Volume",
		"row_count":	1,
		"rows":	[{
				"GUID:s":	"0D8ADD0B_7100D401",
				"DoesCameraColl:d":	1,
				"DoesCameraFade:d":	1,
				"LightChannels:d":	1,
				"ObjectFlags:d":	432,
				"ScriptResource:s":	"",
				"InitialPos:fff":	[-7410.85498046875, 444.35418701171875, -10890.1474609375],
				"Orientation:fff":	[0, 0, 0],
				"LocalBoundingBox:ffffff":	[-129.51034545898437, -268.47344970703125, -420.51889038085937, 129.51034545898437, 268.47344970703125, 420.51889038085937],
				"ObjSaveFlag:d":	0,
				"ObjName:s":	"BatHole Alert Vol",
				"Name:s":	"BatHole Alert Vol",
				"Pos:fff":	[-7410.85498046875, 444.35418701171875, -10890.1474609375],
				"BBox:ffffff":	[-7540.365234375, 175.8807373046875, -11310.666015625, -7281.3447265625, 712.82763671875, -10469.62890625],
				"Orient:fff":	[0, 0, 0],
				"HalfDimensions:fff":	[129.51034545898437, 268.47344970703125, 420.51889038085937],
				"Pain:s":	"none"
			}]
	}, {
		"name":	"Volume",
		"row_count":	1,
		"rows":	[{
				"GUID:s":	"0D8ADD0B_70FEE000",
				"DoesCameraColl:d":	1,
				"DoesCameraFade:d":	1,
				"LightChannels:d":	1,
				"ObjectFlags:d":	432,
				"ScriptResource:s":	"",
				"InitialPos:fff":	[-8378.908203125, 1190.551025390625, -9546.955078125],
				"Orientation:fff":	[0, 0, 0],
				"LocalBoundingBox:ffffff":	[-24.420705795288086, -23.6962833404541, -48.805789947509766, 24.420705795288086, 23.6962833404541, 48.805789947509766],
				"ObjSaveFlag:d":	0,
				"ObjName:s":	"BatHole Vol 001",
				"Name:s":	"BatHole Vol 001",
				"Pos:fff":	[-8378.908203125, 1190.551025390625, -9546.955078125],
				"BBox:ffffff":	[-8403.3291015625, 1166.854736328125, -9595.7607421875, -8354.4873046875, 1214.247314453125, -9498.1494140625],
				"Orient:fff":	[0, 0, 0],
				"HalfDimensions:fff":	[24.420705795288086, 23.6962833404541, 48.805789947509766],
				"Pain:s":	"none"
			}]
	}, {
		"name":	"Volume",
		"row_count":	1,
		"rows":	[{
				"GUID:s":	"0D8ADD0B_71003001",
				"DoesCameraColl:d":	1,
				"DoesCameraFade:d":	1,
				"LightChannels:d":	1,
				"ObjectFlags:d":	432,
				"ScriptResource:s":	"",
				"InitialPos:fff":	[-8287.962890625, 960.10137939453125, -9688.375],
				"Orientation:fff":	[0, 0, 0],
				"LocalBoundingBox:ffffff":	[-24.420705795288086, -23.6962833404541, -48.805789947509766, 24.420705795288086, 23.6962833404541, 48.805789947509766],
				"ObjSaveFlag:d":	0,
				"ObjName:s":	"BatHole Vol 002",
				"Name:s":	"BatHole Vol 002",
				"Pos:fff":	[-8287.962890625, 960.10137939453125, -9688.375],
				"BBox:ffffff":	[-8312.3837890625, 936.40509033203125, -9737.1806640625, -8263.5419921875, 983.79766845703125, -9639.5693359375],
				"Orient:fff":	[0, 0, 0],
				"HalfDimensions:fff":	[24.420705795288086, 23.6962833404541, 48.805789947509766],
				"Pain:s":	"none"
			}]
	}, {
		"name":	"Volume",
		"row_count":	1,
		"rows":	[{
				"GUID:s":	"0D8ADD0B_71005401",
				"DoesCameraColl:d":	1,
				"DoesCameraFade:d":	1,
				"LightChannels:d":	1,
				"ObjectFlags:d":	432,
				"ScriptResource:s":	"",
				"InitialPos:fff":	[-8287.962890625, 572.8858642578125, -9688.375],
				"Orientation:fff":	[0, 0, 0],
				"LocalBoundingBox:ffffff":	[-24.420705795288086, -23.6962833404541, -48.805789947509766, 24.420705795288086, 23.6962833404541, 48.805789947509766],
				"ObjSaveFlag:d":	0,
				"ObjName:s":	"BatHole Vol 003",
				"Name:s":	"BatHole Vol 003",
				"Pos:fff":	[-8287.962890625, 572.8858642578125, -9688.375],
				"BBox:ffffff":	[-8312.3837890625, 549.1895751953125, -9737.1806640625, -8263.5419921875, 596.5821533203125, -9639.5693359375],
				"Orient:fff":	[0, 0, 0],
				"HalfDimensions:fff":	[24.420705795288086, 23.6962833404541, 48.805789947509766],
				"Pain:s":	"none"
			}]
	}, {
		"name":	"Volume",
		"row_count":	1,
		"rows":	[{
				"GUID:s":	"0D8AD40B_48800000",
				"DoesCameraColl:d":	1,
				"DoesCameraFade:d":	1,
				"LightChannels:d":	1,
				"ObjectFlags:d":	432,
				"ScriptResource:s":	"",
				"InitialPos:fff":	[-4224.5712890625, 221.07453918457031, -12279.1875],
				"Orientation:fff":	[0, 0, 0],
				"LocalBoundingBox:ffffff":	[-87.1174774169922, -96.2760772705078, -55.032867431640625, 87.1174774169922, 96.2760772705078, 55.032867431640625],
				"ObjSaveFlag:d":	0,
				"ObjName:s":	"Bilbo VO Vol - Just like climbi",
				"Name:s":	"Bilbo VO Vol - Just like climbi",
				"Pos:fff":	[-4224.5712890625, 221.07453918457031, -12279.1875],
				"BBox:ffffff":	[-4311.68896484375, 124.7984619140625, -12334.220703125, -4137.45361328125, 317.35061645507812, -12224.154296875],
				"Orient:fff":	[0, 0, 0],
				"HalfDimensions:fff":	[87.1174774169922, 96.2760772705078, 55.032867431640625],
				"Pain:s":	"none"
			}]
	}, {
		"name":	"Volume",
		"row_count":	1,
		"rows":	[{
				"GUID:s":	"0D8AD40B_488D1001",
				"DoesCameraColl:d":	1,
				"DoesCameraFade:d":	1,
				"LightChannels:d":	1,
				"ObjectFlags:d":	432,
				"ScriptResource:s":	"",
				"InitialPos:fff":	[-7093.3935546875, 378.52529907226563, -11231.6201171875],
				"Orientation:fff":	[0, -68.399986267089844, 0],
				"LocalBoundingBox:ffffff":	[-244.07083129882812, -144.41410827636719, -235.97123718261719, 244.07083129882812, 144.41410827636719, 235.97123718261719],
				"ObjSaveFlag:d":	0,
				"ObjName:s":	"Bilbo VO Vol - Not another",
				"Name:s":	"Bilbo VO Vol - Not another",
				"Pos:fff":	[-7093.3935546875, 378.52529907226563, -11231.6201171875],
				"BBox:ffffff":	[-7337.46435546875, 234.11119079589844, -11467.591796875, -6849.32275390625, 522.93939208984375, -10995.6484375],
				"Orient:fff":	[0, -68.399986267089844, 0],
				"HalfDimensions:fff":	[177.71961975097656, 144.41410827636719, 192.14065551757812],
				"Pain:s":	"none"
			}]
	}, {
		"name":	"Volume",
		"row_count":	1,
		"rows":	[{
				"GUID:s":	"0D8AD40B_488A4C01",
				"DoesCameraColl:d":	1,
				"DoesCameraFade:d":	1,
				"LightChannels:d":	1,
				"ObjectFlags:d":	432,
				"ScriptResource:s":	"",
				"InitialPos:fff":	[-5318.49365234375, 51.472183227539063, -11500.3642578125],
				"Orientation:fff":	[0, 33.750019073486328, 0],
				"LocalBoundingBox:ffffff":	[-204.03402709960937, -191.85897827148437, -177.81248474121094, 204.03402709960937, 191.85897827148437, 177.81248474121094],
				"ObjSaveFlag:d":	0,
				"ObjName:s":	"Bilbo VO Vol - Sunlight Again",
				"Name:s":	"Bilbo VO Vol - Sunlight Again",
				"Pos:fff":	[-5318.49365234375, 51.472183227539063, -11500.3642578125],
				"BBox:ffffff":	[-5522.52783203125, -140.38679504394531, -11678.1767578125, -5114.45947265625, 243.33116149902344, -11322.5517578125],
				"Orient:fff":	[0, 33.750019073486328, 0],
				"HalfDimensions:fff":	[185.16818237304687, 191.85897827148437, 90.127792358398438],
				"Pain:s":	"none"
			}]
	}, {
		"name":	"Volume",
		"row_count":	1,
		"rows":	[{
				"GUID:s":	"0D8AD40D_281E4000",
				"DoesCameraColl:d":	1,
				"DoesCameraFade:d":	1,
				"LightChannels:d":	1,
				"ObjectFlags:d":	432,
				"ScriptResource:s":	"",
				"InitialPos:fff":	[-6866.69873046875, -1993.492919921875, -15461.18359375],
				"Orientation:fff":	[0, 0, 0],
				"LocalBoundingBox:ffffff":	[-50, -50, -50, 50, 50, 50],
				"ObjSaveFlag:d":	0,
				"ObjName:s":	"Bombur SnapTo",
				"Name:s":	"Bombur SnapTo",
				"Pos:fff":	[-6866.69873046875, -1993.492919921875, -15461.18359375],
				"BBox:ffffff":	[-6916.69873046875, -2043.492919921875, -15511.18359375, -6816.69873046875, -1943.492919921875, -15411.18359375],
				"Orient:fff":	[0, 0, 0],
				"HalfDimensions:fff":	[50, 50, 50],
				"Pain:s":	"none"
			}]
	}, {
		"name":	"Volume",
		"row_count":	1,
		"rows":	[{
				"GUID:s":	"CD588891_07588400",
				"DoesCameraColl:d":	1,
				"DoesCameraFade:d":	1,
				"LightChannels:d":	1,
				"ObjectFlags:d":	432,
				"ScriptResource:s":	"",
				"InitialPos:fff":	[-12028.486328125, 304.04144287109375, -8955.8798828125],
				"Orientation:fff":	[0, 0, 0],
				"LocalBoundingBox:ffffff":	[-50, -50, -50, 50, 50, 50],
				"ObjSaveFlag:d":	0,
				"ObjName:s":	"Camera Influ Target 001",
				"Name:s":	"Camera Influ Target 001",
				"Pos:fff":	[-12028.486328125, 304.04144287109375, -8955.8798828125],
				"BBox:ffffff":	[-12078.486328125, 254.04144287109375, -9005.8798828125, -11978.486328125, 354.04144287109375, -8905.8798828125],
				"Orient:fff":	[0, 0, 0],
				"HalfDimensions:fff":	[50, 50, 50],
				"Pain:s":	"none"
			}]
	}, {
		"name":	"Volume",
		"row_count":	1,
		"rows":	[{
				"GUID:s":	"CD588891_07576000",
				"DoesCameraColl:d":	1,
				"DoesCameraFade:d":	1,
				"LightChannels:d":	1,
				"ObjectFlags:d":	432,
				"ScriptResource:s":	"",
				"InitialPos:fff":	[-11771.0087890625, 489.56314086914062, -8312.7578125],
				"Orientation:fff":	[0, 0, 0],
				"LocalBoundingBox:ffffff":	[-50, -195.58003234863281, -50, 50, 195.58003234863281, 50],
				"ObjSaveFlag:d":	0,
				"ObjName:s":	"Camera Influ Trig 001",
				"Name:s":	"Camera Influ Trig 001",
				"Pos:fff":	[-11771.0087890625, 489.56314086914062, -8312.7578125],
				"BBox:ffffff":	[-11821.0087890625, 293.98309326171875, -8362.7578125, -11721.0087890625, 685.1431884765625, -8262.7578125],
				"Orient:fff":	[0, 0, 0],
				"HalfDimensions:fff":	[50, 195.58003234863281, 50],
				"Pain:s":	"none"
			}]
	}, {
		"name":	"Volume",
		"row_count":	1,
		"rows":	[{
				"GUID:s":	"0D8AD2CD_CB830401",
				"DoesCameraColl:d":	1,
				"DoesCameraFade:d":	1,
				"LightChannels:d":	1,
				"ObjectFlags:d":	432,
				"ScriptResource:s":	"",
				"InitialPos:fff":	[2369.5537109375, -1196.8466796875, -5396.52685546875],
				"Orientation:fff":	[0, 0, 0],
				"LocalBoundingBox:ffffff":	[-50, -50, -50, 50, 50, 50],
				"ObjSaveFlag:d":	0,
				"ObjName:s":	"CaveGuard_Patrol_FaceVol 001",
				"Name:s":	"CaveGuard_Patrol_FaceVol 001",
				"Pos:fff":	[2369.5537109375, -1196.8466796875, -5396.52685546875],
				"BBox:ffffff":	[2319.5537109375, -1246.8466796875, -5446.52685546875, 2419.5537109375, -1146.8466796875, -5346.52685546875],
				"Orient:fff":	[0, 0, 0],
				"HalfDimensions:fff":	[50, 50, 50],
				"Pain:s":	"none"
			}]
	}, {
		"name":	"Volume",
		"row_count":	1,
		"rows":	[{
				"GUID:s":	"0D8AD2CD_CB825001",
				"DoesCameraColl:d":	1,
				"DoesCameraFade:d":	1,
				"LightChannels:d":	1,
				"ObjectFlags:d":	432,
				"ScriptResource:s":	"",
				"InitialPos:fff":	[735.3712158203125, -1192.4296875, -7599.78125],
				"Orientation:fff":	[0, 0, 0],
				"LocalBoundingBox:ffffff":	[-50, -50, -50, 50, 50, 50],
				"ObjSaveFlag:d":	0,
				"ObjName:s":	"CaveGuard_Patrol_FaceVol 003",
				"Name:s":	"CaveGuard_Patrol_FaceVol 003",
				"Pos:fff":	[735.3712158203125, -1192.4296875, -7599.78125],
				"BBox:ffffff":	[685.3712158203125, -1242.4296875, -7649.78125, 785.3712158203125, -1142.4296875, -7549.78125],
				"Orient:fff":	[0, 0, 0],
				"HalfDimensions:fff":	[50, 50, 50],
				"Pain:s":	"none"
			}]
	}, {
		"name":	"Volume",
		"row_count":	1,
		"rows":	[{
				"GUID:s":	"0D8AD2CD_CB812800",
				"DoesCameraColl:d":	1,
				"DoesCameraFade:d":	1,
				"LightChannels:d":	1,
				"ObjectFlags:d":	432,
				"ScriptResource:s":	"",
				"InitialPos:fff":	[2768.48779296875, -1190.2962646484375, -6329.55517578125],
				"Orientation:fff":	[0, 0, 0],
				"LocalBoundingBox:ffffff":	[-50, -50, -50, 50, 50, 50],
				"ObjSaveFlag:d":	0,
				"ObjName:s":	"CaveGuard_Patrol_LocVol 001",
				"Name:s":	"CaveGuard_Patrol_LocVol 001",
				"Pos:fff":	[2768.48779296875, -1190.2962646484375, -6329.55517578125],
				"BBox:ffffff":	[2718.48779296875, -1240.2962646484375, -6379.55517578125, 2818.48779296875, -1140.2962646484375, -6279.55517578125],
				"Orient:fff":	[0, 0, 0],
				"HalfDimensions:fff":	[50, 50, 50],
				"Pain:s":	"none"
			}]
	}, {
		"name":	"Volume",
		"row_count":	1,
		"rows":	[{
				"GUID:s":	"0D8AD2CD_CB81D800",
				"DoesCameraColl:d":	1,
				"DoesCameraFade:d":	1,
				"LightChannels:d":	1,
				"ObjectFlags:d":	432,
				"ScriptResource:s":	"",
				"InitialPos:fff":	[1840.501708984375, -1188.1109619140625, -6462.94482421875],
				"Orientation:fff":	[0, 0, 0],
				"LocalBoundingBox:ffffff":	[-50, -50, -50, 50, 50, 50],
				"ObjSaveFlag:d":	0,
				"ObjName:s":	"CaveGuard_Patrol_LocVol 002",
				"Name:s":	"CaveGuard_Patrol_LocVol 002",
				"Pos:fff":	[1840.501708984375, -1188.1109619140625, -6462.94482421875],
				"BBox:ffffff":	[1790.501708984375, -1238.1109619140625, -6512.94482421875, 1890.501708984375, -1138.1109619140625, -6412.94482421875],
				"Orient:fff":	[0, 0, 0],
				"HalfDimensions:fff":	[50, 50, 50],
				"Pain:s":	"none"
			}]
	}, {
		"name":	"Volume",
		"row_count":	1,
		"rows":	[{
				"GUID:s":	"0D8AD2CD_CB81F001",
				"DoesCameraColl:d":	1,
				"DoesCameraFade:d":	1,
				"LightChannels:d":	1,
				"ObjectFlags:d":	432,
				"ScriptResource:s":	"",
				"InitialPos:fff":	[1453.8638916015625, -1191.2554931640625, -7490.03369140625],
				"Orientation:fff":	[0, 0, 0],
				"LocalBoundingBox:ffffff":	[-50, -50, -50, 50, 50, 50],
				"ObjSaveFlag:d":	0,
				"ObjName:s":	"CaveGuard_Patrol_LocVol 003",
				"Name:s":	"CaveGuard_Patrol_LocVol 003",
				"Pos:fff":	[1453.8638916015625, -1191.2554931640625, -7490.03369140625],
				"BBox:ffffff":	[1403.8638916015625, -1241.2554931640625, -7540.03369140625, 1503.8638916015625, -1141.2554931640625, -7440.03369140625],
				"Orient:fff":	[0, 0, 0],
				"HalfDimensions:fff":	[50, 50, 50],
				"Pain:s":	"none"
			}]
	}, {
		"name":	"Volume",
		"row_count":	1,
		"rows":	[{
				"GUID:s":	"0D8AD2CF_60853800",
				"DoesCameraColl:d":	1,
				"DoesCameraFade:d":	1,
				"LightChannels:d":	1,
				"ObjectFlags:d":	432,
				"ScriptResource:s":	"",
				"InitialPos:fff":	[-3997.712158203125, -1144.54833984375, -21371.728515625],
				"Orientation:fff":	[0, 0, 0],
				"LocalBoundingBox:ffffff":	[-223.47999572753906, -274.61465454101562, -248.25498962402344, 223.47999572753906, 274.61465454101562, 248.25498962402344],
				"ObjSaveFlag:d":	0,
				"ObjName:s":	"DEBUG EOL Vol",
				"Name:s":	"DEBUG EOL Vol",
				"Pos:fff":	[-3997.712158203125, -1144.54833984375, -21371.728515625],
				"BBox:ffffff":	[-4221.1923828125, -1419.1629638671875, -21619.984375, -3774.232177734375, -869.9337158203125, -21123.47265625],
				"Orient:fff":	[0, 0, 0],
				"HalfDimensions:fff":	[223.47999572753906, 274.61465454101562, 248.25498962402344],
				"Pain:s":	"none"
			}]
	}, {
		"name":	"Volume",
		"row_count":	1,
		"rows":	[{
				"GUID:s":	"0D8AD40D_281E8001",
				"DoesCameraColl:d":	1,
				"DoesCameraFade:d":	1,
				"LightChannels:d":	1,
				"ObjectFlags:d":	432,
				"ScriptResource:s":	"",
				"InitialPos:fff":	[-7027.75146484375, -1975.810546875, -15354.8046875],
				"Orientation:fff":	[0, 0, 0],
				"LocalBoundingBox:ffffff":	[-50, -50, -50, 50, 50, 50],
				"ObjSaveFlag:d":	0,
				"ObjName:s":	"Dwalin SnapTo",
				"Name:s":	"Dwalin SnapTo",
				"Pos:fff":	[-7027.75146484375, -1975.810546875, -15354.8046875],
				"BBox:ffffff":	[-7077.75146484375, -2025.810546875, -15404.8046875, -6977.75146484375, -1925.810546875, -15304.8046875],
				"Orient:fff":	[0, 0, 0],
				"HalfDimensions:fff":	[50, 50, 50],
				"Pain:s":	"none"
			}]
	}, {
		"name":	"Volume",
		"row_count":	1,
		"rows":	[{
				"GUID:s":	"0D8AD40D_281EA801",
				"DoesCameraColl:d":	1,
				"DoesCameraFade:d":	1,
				"LightChannels:d":	1,
				"ObjectFlags:d":	432,
				"ScriptResource:s":	"",
				"InitialPos:fff":	[-6879.25, -1930.806396484375, -14983.8349609375],
				"Orientation:fff":	[0, 0, 0],
				"LocalBoundingBox:ffffff":	[-50, -50, -50, 50, 50, 50],
				"ObjSaveFlag:d":	0,
				"ObjName:s":	"Dwarf SnapTo_Face",
				"Name:s":	"Dwarf SnapTo_Face",
				"Pos:fff":	[-6879.25, -1930.806396484375, -14983.8349609375],
				"BBox:ffffff":	[-6929.25, -1980.806396484375, -15033.8349609375, -6829.25, -1880.806396484375, -14933.8349609375],
				"Orient:fff":	[0, 0, 0],
				"HalfDimensions:fff":	[50, 50, 50],
				"Pain:s":	"none"
			}]
	}, {
		"name":	"Volume",
		"row_count":	1,
		"rows":	[{
				"GUID:s":	"0D8AD48C_9826E001",
				"DoesCameraColl:d":	1,
				"DoesCameraFade:d":	1,
				"LightChannels:d":	1,
				"ObjectFlags:d":	432,
				"ScriptResource:s":	"",
				"InitialPos:fff":	[-6288.1064453125, 1023.9451904296875, -10761.578125],
				"Orientation:fff":	[0, 0, 0],
				"LocalBoundingBox:ffffff":	[-50, -50, -50, 50, 50, 50],
				"ObjSaveFlag:d":	0,
				"ObjName:s":	"FB10 FaceVol",
				"Name:s":	"FB10 FaceVol",
				"Pos:fff":	[-6288.1064453125, 1023.9451904296875, -10761.578125],
				"BBox:ffffff":	[-6338.1064453125, 973.9451904296875, -10811.578125, -6238.1064453125, 1073.9451904296875, -10711.578125],
				"Orient:fff":	[0, 0, 0],
				"HalfDimensions:fff":	[50, 50, 50],
				"Pain:s":	"none"
			}]
	}, {
		"name":	"Volume",
		"row_count":	1,
		"rows":	[{
				"GUID:s":	"0D8AD48C_98273801",
				"DoesCameraColl:d":	1,
				"DoesCameraFade:d":	1,
				"LightChannels:d":	1,
				"ObjectFlags:d":	432,
				"ScriptResource:s":	"",
				"InitialPos:fff":	[-6345.705078125, 813.66546630859375, -11338.1748046875],
				"Orientation:fff":	[0, 0, 0],
				"LocalBoundingBox:ffffff":	[-453.98895263671875, -294.34994506835937, -102.50000762939453, 453.98895263671875, 294.34994506835937, 102.50000762939453],
				"ObjSaveFlag:d":	0,
				"ObjName:s":	"FB10 Spawn TrigVol",
				"Name:s":	"FB10 Spawn TrigVol",
				"Pos:fff":	[-6345.705078125, 813.66546630859375, -11338.1748046875],
				"BBox:ffffff":	[-6799.69384765625, 519.3155517578125, -11440.6748046875, -5891.71630859375, 1108.015380859375, -11235.6748046875],
				"Orient:fff":	[0, 0, 0],
				"HalfDimensions:fff":	[453.98895263671875, 294.34994506835937, 102.50000762939453],
				"Pain:s":	"none"
			}]
	}, {
		"name":	"Volume",
		"row_count":	1,
		"rows":	[{
				"GUID:s":	"0D8AD48C_98267400",
				"DoesCameraColl:d":	1,
				"DoesCameraFade:d":	1,
				"LightChannels:d":	1,
				"ObjectFlags:d":	432,
				"ScriptResource:s":	"",
				"InitialPos:fff":	[-6080.02099609375, 1023.9451904296875, -10409.408203125],
				"Orientation:fff":	[0, 0, 0],
				"LocalBoundingBox:ffffff":	[-50, -50, -50, 50, 50, 50],
				"ObjSaveFlag:d":	0,
				"ObjName:s":	"FB10 SpawnVol",
				"Name:s":	"FB10 SpawnVol",
				"Pos:fff":	[-6080.02099609375, 1023.9451904296875, -10409.408203125],
				"BBox:ffffff":	[-6130.02099609375, 973.9451904296875, -10459.408203125, -6030.02099609375, 1073.9451904296875, -10359.408203125],
				"Orient:fff":	[0, 0, 0],
				"HalfDimensions:fff":	[50, 50, 50],
				"Pain:s":	"none"
			}]
	}, {
		"name":	"Volume",
		"row_count":	1,
		"rows":	[{
				"GUID:s":	"0D8AD48C_982A8801",
				"DoesCameraColl:d":	1,
				"DoesCameraFade:d":	1,
				"LightChannels:d":	1,
				"ObjectFlags:d":	432,
				"ScriptResource:s":	"",
				"InitialPos:fff":	[-6707.35205078125, 1023.9451904296875, -10199.1787109375],
				"Orientation:fff":	[0, 0, 0],
				"LocalBoundingBox:ffffff":	[-50, -50, -50, 50, 50, 50],
				"ObjSaveFlag:d":	0,
				"ObjName:s":	"FB15 SpawnVol",
				"Name:s":	"FB15 SpawnVol",
				"Pos:fff":	[-6707.35205078125, 1023.9451904296875, -10199.1787109375],
				"BBox:ffffff":	[-6757.35205078125, 973.9451904296875, -10249.1787109375, -6657.35205078125, 1073.9451904296875, -10149.1787109375],
				"Orient:fff":	[0, 0, 0],
				"HalfDimensions:fff":	[50, 50, 50],
				"Pain:s":	"none"
			}]
	}, {
		"name":	"Volume",
		"row_count":	1,
		"rows":	[{
				"GUID:s":	"CD588C91_D4175000",
				"DoesCameraColl:d":	1,
				"DoesCameraFade:d":	1,
				"LightChannels:d":	1,
				"ObjectFlags:d":	432,
				"ScriptResource:s":	"",
				"InitialPos:fff":	[-6566.2138671875, -1277.5390625, -18035.083984375],
				"Orientation:fff":	[0, 0, 0],
				"LocalBoundingBox:ffffff":	[-50, -50, -50, 50, 50, 50],
				"ObjSaveFlag:d":	0,
				"ObjName:s":	"FaceVol - Balin",
				"Name:s":	"FaceVol - Balin",
				"Pos:fff":	[-6566.2138671875, -1277.5390625, -18035.083984375],
				"BBox:ffffff":	[-6616.2138671875, -1327.5390625, -18085.083984375, -6516.2138671875, -1227.5390625, -17985.083984375],
				"Orient:fff":	[0, 0, 0],
				"HalfDimensions:fff":	[50, 50, 50],
				"Pain:s":	"none"
			}]
	}, {
		"name":	"Volume",
		"row_count":	1,
		"rows":	[{
				"GUID:s":	"CD5889D2_3808A001",
				"DoesCameraColl:d":	1,
				"DoesCameraFade:d":	1,
				"LightChannels:d":	1,
				"ObjectFlags:d":	432,
				"ScriptResource:s":	"",
				"InitialPos:fff":	[-6438.73193359375, -1254.526123046875, -18315.07421875],
				"Orientation:fff":	[0, 0, 0],
				"LocalBoundingBox:ffffff":	[-50, -50, -50, 50, 50, 50],
				"ObjSaveFlag:d":	0,
				"ObjName:s":	"FaceVol - Thorin",
				"Name:s":	"FaceVol - Thorin",
				"Pos:fff":	[-6438.73193359375, -1254.526123046875, -18315.07421875],
				"BBox:ffffff":	[-6488.73193359375, -1304.526123046875, -18365.07421875, -6388.73193359375, -1204.526123046875, -18265.07421875],
				"Orient:fff":	[0, 0, 0],
				"HalfDimensions:fff":	[50, 50, 50],
				"Pain:s":	"none"
			}]
	}, {
		"name":	"Volume",
		"row_count":	1,
		"rows":	[{
				"GUID:s":	"0D8AD1CC_938C7000",
				"DoesCameraColl:d":	1,
				"DoesCameraFade:d":	1,
				"LightChannels:d":	1,
				"ObjectFlags:d":	432,
				"ScriptResource:s":	"",
				"InitialPos:fff":	[-6012.91845703125, -1306.72412109375, -18307.20703125],
				"Orientation:fff":	[0, -10.350024223327637, 0],
				"LocalBoundingBox:ffffff":	[-52.6458740234375, -118.37456512451172, -49.574665069580078, 52.6458740234375, 118.37456512451172, 49.574665069580078],
				"ObjSaveFlag:d":	0,
				"ObjName:s":	"Gandalf Main Quest TrigVol",
				"Name:s":	"Gandalf Main Quest TrigVol",
				"Pos:fff":	[-6012.91845703125, -1306.72412109375, -18307.20703125],
				"BBox:ffffff":	[-6065.564453125, -1425.0986328125, -18356.78125, -5960.2724609375, -1188.349609375, -18257.6328125],
				"Orient:fff":	[0, -10.350024223327637, 0],
				"HalfDimensions:fff":	[45.841999053955078, 118.37456512451172, 42.022403717041016],
				"Pain:s":	"none"
			}]
	}, {
		"name":	"Volume",
		"row_count":	1,
		"rows":	[{
				"GUID:s":	"0D8AD08C_93446000",
				"DoesCameraColl:d":	1,
				"DoesCameraFade:d":	1,
				"LightChannels:d":	1,
				"ObjectFlags:d":	432,
				"ScriptResource:s":	"",
				"InitialPos:fff":	[910.34027099609375, -1125.4022216796875, -9247.0390625],
				"Orientation:fff":	[0, -15.749978065490723, 0],
				"LocalBoundingBox:ffffff":	[-395.70053100585937, -174.99998474121094, -155.89401245117187, 395.70053100585937, 174.99998474121094, 155.89401245117187],
				"ObjSaveFlag:d":	0,
				"ObjName:s":	"Lianna Convo TrigVol",
				"Name:s":	"Lianna Convo TrigVol",
				"Pos:fff":	[910.34027099609375, -1125.4022216796875, -9247.0390625],
				"BBox:ffffff":	[514.6397705078125, -1300.4022216796875, -9402.9326171875, 1306.040771484375, -950.4022216796875, -9091.1455078125],
				"Orient:fff":	[0, -15.749978065490723, 0],
				"HalfDimensions:fff":	[397.03509521484375, 174.99998474121094, 50],
				"Pain:s":	"none"
			}]
	}, {
		"name":	"Volume",
		"row_count":	1,
		"rows":	[{
				"GUID:s":	"63CA7650_83C42C01",
				"DoesCameraColl:d":	1,
				"DoesCameraFade:d":	1,
				"LightChannels:d":	1,
				"ObjectFlags:d":	432,
				"ScriptResource:s":	"",
				"InitialPos:fff":	[2754.717041015625, -1121.8763427734375, -6904.337890625],
				"Orientation:fff":	[0, 0, 0],
				"LocalBoundingBox:ffffff":	[-50, -50, -50, 50, 50, 50],
				"ObjSaveFlag:d":	0,
				"ObjName:s":	"LittleRockMinionFacing001",
				"Name:s":	"LittleRockMinionFacing001",
				"Pos:fff":	[2754.717041015625, -1121.8763427734375, -6904.337890625],
				"BBox:ffffff":	[2704.717041015625, -1171.8763427734375, -6954.337890625, 2804.717041015625, -1071.8763427734375, -6854.337890625],
				"Orient:fff":	[0, 0, 0],
				"HalfDimensions:fff":	[50, 50, 50],
				"Pain:s":	"none"
			}]
	}, {
		"name":	"Volume",
		"row_count":	1,
		"rows":	[{
				"GUID:s":	"63CA7650_83C48C01",
				"DoesCameraColl:d":	1,
				"DoesCameraFade:d":	1,
				"LightChannels:d":	1,
				"ObjectFlags:d":	432,
				"ScriptResource:s":	"",
				"InitialPos:fff":	[2595.1865234375, -1121.876220703125, -7525.3818359375],
				"Orientation:fff":	[0, 0, 0],
				"LocalBoundingBox:ffffff":	[-50, -50, -50, 50, 50, 50],
				"ObjSaveFlag:d":	0,
				"ObjName:s":	"LittleRockMinionFacing002",
				"Name:s":	"LittleRockMinionFacing002",
				"Pos:fff":	[2595.1865234375, -1121.876220703125, -7525.3818359375],
				"BBox:ffffff":	[2545.1865234375, -1171.876220703125, -7575.3818359375, 2645.1865234375, -1071.876220703125, -7475.3818359375],
				"Orient:fff":	[0, 0, 0],
				"HalfDimensions:fff":	[50, 50, 50],
				"Pain:s":	"none"
			}]
	}, {
		"name":	"Volume",
		"row_count":	1,
		"rows":	[{
				"GUID:s":	"63CA7650_83C4B801",
				"DoesCameraColl:d":	1,
				"DoesCameraFade:d":	1,
				"LightChannels:d":	1,
				"ObjectFlags:d":	432,
				"ScriptResource:s":	"",
				"InitialPos:fff":	[2784.663818359375, -1121.8763427734375, -6521.96044921875],
				"Orientation:fff":	[0, 0, 0],
				"LocalBoundingBox:ffffff":	[-50, -50, -50, 50, 50, 50],
				"ObjSaveFlag:d":	0,
				"ObjName:s":	"LittleRockMinionFacing003",
				"Name:s":	"LittleRockMinionFacing003",
				"Pos:fff":	[2784.663818359375, -1121.8763427734375, -6521.96044921875],
				"BBox:ffffff":	[2734.663818359375, -1171.8763427734375, -6571.96044921875, 2834.663818359375, -1071.8763427734375, -6471.96044921875],
				"Orient:fff":	[0, 0, 0],
				"HalfDimensions:fff":	[50, 50, 50],
				"Pain:s":	"none"
			}]
	}, {
		"name":	"Volume",
		"row_count":	1,
		"rows":	[{
				"GUID:s":	"63CA7650_83C1A801",
				"DoesCameraColl:d":	1,
				"DoesCameraFade:d":	1,
				"LightChannels:d":	1,
				"ObjectFlags:d":	432,
				"ScriptResource:s":	"",
				"InitialPos:fff":	[2948.531982421875, -1121.8763427734375, -6904.337890625],
				"Orientation:fff":	[0, 0, 0],
				"LocalBoundingBox:ffffff":	[-50, -50, -50, 50, 50, 50],
				"ObjSaveFlag:d":	0,
				"ObjName:s":	"LittleRockMinionSpawn001",
				"Name:s":	"LittleRockMinionSpawn001",
				"Pos:fff":	[2948.531982421875, -1121.8763427734375, -6904.337890625],
				"BBox:ffffff":	[2898.531982421875, -1171.8763427734375, -6954.337890625, 2998.531982421875, -1071.8763427734375, -6854.337890625],
				"Orient:fff":	[0, 0, 0],
				"HalfDimensions:fff":	[50, 50, 50],
				"Pain:s":	"none"
			}]
	}, {
		"name":	"Volume",
		"row_count":	1,
		"rows":	[{
				"GUID:s":	"63CA7650_83C29C01",
				"DoesCameraColl:d":	1,
				"DoesCameraFade:d":	1,
				"LightChannels:d":	1,
				"ObjectFlags:d":	432,
				"ScriptResource:s":	"",
				"InitialPos:fff":	[2753.549072265625, -1120.345458984375, -7605.7001953125],
				"Orientation:fff":	[0, 0, 0],
				"LocalBoundingBox:ffffff":	[-50, -50, -50, 50, 50, 50],
				"ObjSaveFlag:d":	0,
				"ObjName:s":	"LittleRockMinionSpawn002",
				"Name:s":	"LittleRockMinionSpawn002",
				"Pos:fff":	[2753.549072265625, -1120.345458984375, -7605.7001953125],
				"BBox:ffffff":	[2703.549072265625, -1170.345458984375, -7655.7001953125, 2803.549072265625, -1070.345458984375, -7555.7001953125],
				"Orient:fff":	[0, 0, 0],
				"HalfDimensions:fff":	[50, 50, 50],
				"Pain:s":	"none"
			}]
	}, {
		"name":	"Volume",
		"row_count":	1,
		"rows":	[{
				"GUID:s":	"63CA7650_83C2D801",
				"DoesCameraColl:d":	1,
				"DoesCameraFade:d":	1,
				"LightChannels:d":	1,
				"ObjectFlags:d":	432,
				"ScriptResource:s":	"",
				"InitialPos:fff":	[2977.8427734375, -1124.747314453125, -6514.09716796875],
				"Orientation:fff":	[0, 0, 0],
				"LocalBoundingBox:ffffff":	[-50, -50, -50, 50, 50, 50],
				"ObjSaveFlag:d":	0,
				"ObjName:s":	"LittleRockMinionSpawn003",
				"Name:s":	"LittleRockMinionSpawn003",
				"Pos:fff":	[2977.8427734375, -1124.747314453125, -6514.09716796875],
				"BBox:ffffff":	[2927.8427734375, -1174.747314453125, -6564.09716796875, 3027.8427734375, -1074.747314453125, -6464.09716796875],
				"Orient:fff":	[0, 0, 0],
				"HalfDimensions:fff":	[50, 50, 50],
				"Pain:s":	"none"
			}]
	}, {
		"name":	"Volume",
		"row_count":	1,
		"rows":	[{
				"GUID:s":	"CD588412_C20C3C00",
				"DoesCameraColl:d":	1,
				"DoesCameraFade:d":	1,
				"LightChannels:d":	1,
				"ObjectFlags:d":	432,
				"ScriptResource:s":	"",
				"InitialPos:fff":	[949.5743408203125, -1063.4825439453125, -8448.8115234375],
				"Orientation:fff":	[0, 5.850013256072998, 0],
				"LocalBoundingBox:ffffff":	[-554.1021728515625, -428.45660400390625, -105.98980712890625, 554.1021728515625, 428.45660400390625, 105.98980712890625],
				"ObjSaveFlag:d":	0,
				"ObjName:s":	"Overlay Cave Guardian Hint",
				"Name:s":	"Overlay Cave Guardian Hint",
				"Pos:fff":	[949.5743408203125, -1063.4825439453125, -8448.8115234375],
				"BBox:ffffff":	[395.47216796875, -1491.939208984375, -8554.8017578125, 1503.676513671875, -635.02593994140625, -8342.8212890625],
				"Orient:fff":	[0, 5.850013256072998, 0],
				"HalfDimensions:fff":	[551.88006591796875, 428.45660400390625, 50],
				"Pain:s":	"none"
			}]
	}, {
		"name":	"Volume",
		"row_count":	1,
		"rows":	[{
				"GUID:s":	"0D8ADF0B_70D13401",
				"DoesCameraColl:d":	1,
				"DoesCameraFade:d":	1,
				"LightChannels:d":	1,
				"ObjectFlags:d":	432,
				"ScriptResource:s":	"",
				"InitialPos:fff":	[-2103.236572265625, -960.96649169921875, -5367.10205078125],
				"Orientation:fff":	[0, 0, 0],
				"LocalBoundingBox:ffffff":	[-956.563232421875, -286.83944702148437, -434.10806274414062, 956.563232421875, 286.83944702148437, 434.10806274414062],
				"ObjSaveFlag:d":	0,
				"ObjName:s":	"Pit Trap Alert Vol",
				"Name:s":	"Pit Trap Alert Vol",
				"Pos:fff":	[-2103.236572265625, -960.96649169921875, -5367.10205078125],
				"BBox:ffffff":	[-3059.7998046875, -1247.805908203125, -5801.2099609375, -1146.67333984375, -674.1270751953125, -4932.994140625],
				"Orient:fff":	[0, 0, 0],
				"HalfDimensions:fff":	[956.563232421875, 286.83944702148437, 434.10806274414062],
				"Pain:s":	"none"
			}]
	}, {
		"name":	"Volume",
		"row_count":	1,
		"rows":	[{
				"GUID:s":	"0D8ADF0B_70CFA800",
				"DoesCameraColl:d":	1,
				"DoesCameraFade:d":	1,
				"LightChannels:d":	1,
				"ObjectFlags:d":	432,
				"ScriptResource:s":	"",
				"InitialPos:fff":	[-3282.906494140625, -2401.91650390625, -4759.80224609375],
				"Orientation:fff":	[0, 0, 0],
				"LocalBoundingBox:ffffff":	[-50.307453155517578, -64.187149047851562, -46.611667633056641, 50.307453155517578, 64.187149047851562, 46.611667633056641],
				"ObjSaveFlag:d":	0,
				"ObjName:s":	"Pit Vol 001",
				"Name:s":	"Pit Vol 001",
				"Pos:fff":	[-3282.906494140625, -2401.91650390625, -4759.80224609375],
				"BBox:ffffff":	[-3333.2138671875, -2466.103759765625, -4806.4140625, -3232.59912109375, -2337.729248046875, -4713.1904296875],
				"Orient:fff":	[0, 0, 0],
				"HalfDimensions:fff":	[50.307453155517578, 64.187149047851562, 46.611667633056641],
				"Pain:s":	"none"
			}]
	}, {
		"name":	"Volume",
		"row_count":	1,
		"rows":	[{
				"GUID:s":	"0D8ADF0B_70D07C01",
				"DoesCameraColl:d":	1,
				"DoesCameraFade:d":	1,
				"LightChannels:d":	1,
				"ObjectFlags:d":	432,
				"ScriptResource:s":	"",
				"InitialPos:fff":	[-3079.190673828125, -1705.682861328125, -4821.11767578125],
				"Orientation:fff":	[0, 0, 0],
				"LocalBoundingBox:ffffff":	[-50.307453155517578, -64.187149047851562, -46.611667633056641, 50.307453155517578, 64.187149047851562, 46.611667633056641],
				"ObjSaveFlag:d":	0,
				"ObjName:s":	"Pit Vol 002",
				"Name:s":	"Pit Vol 002",
				"Pos:fff":	[-3079.190673828125, -1705.682861328125, -4821.11767578125],
				"BBox:ffffff":	[-3129.498046875, -1769.8699951171875, -4867.7294921875, -3028.88330078125, -1641.4957275390625, -4774.505859375],
				"Orient:fff":	[0, 0, 0],
				"HalfDimensions:fff":	[50.307453155517578, 64.187149047851562, 46.611667633056641],
				"Pain:s":	"none"
			}]
	}, {
		"name":	"Volume",
		"row_count":	1,
		"rows":	[{
				"GUID:s":	"0D8ADF0B_70D09C01",
				"DoesCameraColl:d":	1,
				"DoesCameraFade:d":	1,
				"LightChannels:d":	1,
				"ObjectFlags:d":	432,
				"ScriptResource:s":	"",
				"InitialPos:fff":	[-2948.76025390625, -1215.911376953125, -5019.126953125],
				"Orientation:fff":	[0, 0, 0],
				"LocalBoundingBox:ffffff":	[-50.307453155517578, -64.187149047851562, -46.611667633056641, 50.307453155517578, 64.187149047851562, 46.611667633056641],
				"ObjSaveFlag:d":	0,
				"ObjName:s":	"Pit Vol 003",
				"Name:s":	"Pit Vol 003",
				"Pos:fff":	[-2948.76025390625, -1215.911376953125, -5019.126953125],
				"BBox:ffffff":	[-2999.067626953125, -1280.0985107421875, -5065.73876953125, -2898.452880859375, -1151.7242431640625, -4972.51513671875],
				"Orient:fff":	[0, 0, 0],
				"HalfDimensions:fff":	[50.307453155517578, 64.187149047851562, 46.611667633056641],
				"Pain:s":	"none"
			}]
	}, {
		"name":	"Volume",
		"row_count":	1,
		"rows":	[{
				"GUID:s":	"0D8ADF0B_70D0D801",
				"DoesCameraColl:d":	1,
				"DoesCameraFade:d":	1,
				"LightChannels:d":	1,
				"ObjectFlags:d":	432,
				"ScriptResource:s":	"",
				"InitialPos:fff":	[-2471.331787109375, -960.965576171875, -5232.0927734375],
				"Orientation:fff":	[0, 0, 0],
				"LocalBoundingBox:ffffff":	[-50.307453155517578, -64.187149047851562, -46.611667633056641, 50.307453155517578, 64.187149047851562, 46.611667633056641],
				"ObjSaveFlag:d":	0,
				"ObjName:s":	"Pit Vol 004",
				"Name:s":	"Pit Vol 004",
				"Pos:fff":	[-2471.331787109375, -960.965576171875, -5232.0927734375],
				"BBox:ffffff":	[-2521.63916015625, -1025.1527099609375, -5278.70458984375, -2421.0244140625, -896.7784423828125, -5185.48095703125],
				"Orient:fff":	[0, 0, 0],
				"HalfDimensions:fff":	[50.307453155517578, 64.187149047851562, 46.611667633056641],
				"Pain:s":	"none"
			}]
	}, {
		"name":	"Volume",
		"row_count":	1,
		"rows":	[{
				"GUID:s":	"0D8AD40D_281CB800",
				"DoesCameraColl:d":	1,
				"DoesCameraFade:d":	1,
				"LightChannels:d":	1,
				"ObjectFlags:d":	432,
				"ScriptResource:s":	"",
				"InitialPos:fff":	[-6339.638671875, -2003.705322265625, -15865.123046875],
				"Orientation:fff":	[0, 0, 0],
				"LocalBoundingBox:ffffff":	[-50, -50, -50, 50, 50, 50],
				"ObjSaveFlag:d":	0,
				"ObjName:s":	"Pony 001 SnapTo",
				"Name:s":	"Pony 001 SnapTo",
				"Pos:fff":	[-6339.638671875, -2003.705322265625, -15865.123046875],
				"BBox:ffffff":	[-6389.638671875, -2053.705322265625, -15915.123046875, -6289.638671875, -1953.705322265625, -15815.123046875],
				"Orient:fff":	[0, 0, 0],
				"HalfDimensions:fff":	[50, 50, 50],
				"Pain:s":	"none"
			}]
	}, {
		"name":	"Volume",
		"row_count":	1,
		"rows":	[{
				"GUID:s":	"0D8AD40D_281D2001",
				"DoesCameraColl:d":	1,
				"DoesCameraFade:d":	1,
				"LightChannels:d":	1,
				"ObjectFlags:d":	432,
				"ScriptResource:s":	"",
				"InitialPos:fff":	[-6358.79541015625, -2009.5302734375, -15616.490234375],
				"Orientation:fff":	[0, 0, 0],
				"LocalBoundingBox:ffffff":	[-50, -50, -50, 50, 50, 50],
				"ObjSaveFlag:d":	0,
				"ObjName:s":	"Pony 001 SnapTo_Face",
				"Name:s":	"Pony 001 SnapTo_Face",
				"Pos:fff":	[-6358.79541015625, -2009.5302734375, -15616.490234375],
				"BBox:ffffff":	[-6408.79541015625, -2059.5302734375, -15666.490234375, -6308.79541015625, -1959.5302734375, -15566.490234375],
				"Orient:fff":	[0, 0, 0],
				"HalfDimensions:fff":	[50, 50, 50],
				"Pain:s":	"none"
			}]
	}, {
		"name":	"Volume",
		"row_count":	1,
		"rows":	[{
				"GUID:s":	"0D8AD40D_281D7804",
				"DoesCameraColl:d":	1,
				"DoesCameraFade:d":	1,
				"LightChannels:d":	1,
				"ObjectFlags:d":	432,
				"ScriptResource:s":	"",
				"InitialPos:fff":	[-6977.43701171875, -2004.4420166015625, -15609.4736328125],
				"Orientation:fff":	[0, 0, 0],
				"LocalBoundingBox:ffffff":	[-50, -50, -50, 50, 50, 50],
				"ObjSaveFlag:d":	0,
				"ObjName:s":	"Pony 002 SnapTo",
				"Name:s":	"Pony 002 SnapTo",
				"Pos:fff":	[-6977.43701171875, -2004.4420166015625, -15609.4736328125],
				"BBox:ffffff":	[-7027.43701171875, -2054.44189453125, -15659.4736328125, -6927.43701171875, -1954.4420166015625, -15559.4736328125],
				"Orient:fff":	[0, 0, 0],
				"HalfDimensions:fff":	[50, 50, 50],
				"Pain:s":	"none"
			}]
	}, {
		"name":	"Volume",
		"row_count":	1,
		"rows":	[{
				"GUID:s":	"0D8AD40D_281D7802",
				"DoesCameraColl:d":	1,
				"DoesCameraFade:d":	1,
				"LightChannels:d":	1,
				"ObjectFlags:d":	432,
				"ScriptResource:s":	"",
				"InitialPos:fff":	[-6665.13818359375, -2011.129638671875, -15610.09765625],
				"Orientation:fff":	[0, 0, 0],
				"LocalBoundingBox:ffffff":	[-50, -50, -50, 50, 50, 50],
				"ObjSaveFlag:d":	0,
				"ObjName:s":	"Pony 002 SnapTo_Face",
				"Name:s":	"Pony 002 SnapTo_Face",
				"Pos:fff":	[-6665.13818359375, -2011.129638671875, -15610.09765625],
				"BBox:ffffff":	[-6715.13818359375, -2061.129638671875, -15660.09765625, -6615.13818359375, -1961.129638671875, -15560.09765625],
				"Orient:fff":	[0, 0, 0],
				"HalfDimensions:fff":	[50, 50, 50],
				"Pain:s":	"none"
			}]
	}, {
		"name":	"Volume",
		"row_count":	1,
		"rows":	[{
				"GUID:s":	"0D8ADE8D_B60EA801",
				"DoesCameraColl:d":	1,
				"DoesCameraFade:d":	1,
				"LightChannels:d":	1,
				"ObjectFlags:d":	432,
				"ScriptResource:s":	"",
				"InitialPos:fff":	[-6305.66015625, -691.16168212890625, -2491.47998046875],
				"Orientation:fff":	[0, 0, 0],
				"LocalBoundingBox:ffffff":	[-50, -50, -50, 50, 50, 50],
				"ObjSaveFlag:d":	0,
				"ObjName:s":	"RB19 FaceVol",
				"Name:s":	"RB19 FaceVol",
				"Pos:fff":	[-6305.66015625, -691.16168212890625, -2491.47998046875],
				"BBox:ffffff":	[-6355.66015625, -741.16168212890625, -2541.47998046875, -6255.66015625, -641.16168212890625, -2441.47998046875],
				"Orient:fff":	[0, 0, 0],
				"HalfDimensions:fff":	[50, 50, 50],
				"Pain:s":	"none"
			}]
	}, {
		"name":	"Volume",
		"row_count":	1,
		"rows":	[{
				"GUID:s":	"0D8ADE8D_B60DE800",
				"DoesCameraColl:d":	1,
				"DoesCameraFade:d":	1,
				"LightChannels:d":	1,
				"ObjectFlags:d":	432,
				"ScriptResource:s":	"",
				"InitialPos:fff":	[-6036.52197265625, -671.41473388671875, -2452.757080078125],
				"Orientation:fff":	[0, 0, 0],
				"LocalBoundingBox:ffffff":	[-50, -50, -50, 50, 50, 50],
				"ObjSaveFlag:d":	0,
				"ObjName:s":	"RB19 LocVol",
				"Name:s":	"RB19 LocVol",
				"Pos:fff":	[-6036.52197265625, -671.41473388671875, -2452.757080078125],
				"BBox:ffffff":	[-6086.52197265625, -721.41473388671875, -2502.757080078125, -5986.52197265625, -621.41473388671875, -2402.757080078125],
				"Orient:fff":	[0, 0, 0],
				"HalfDimensions:fff":	[50, 50, 50],
				"Pain:s":	"none"
			}]
	}, {
		"name":	"Volume",
		"row_count":	1,
		"rows":	[{
				"GUID:s":	"0D8ADA4B_46DCA000",
				"DoesCameraColl:d":	1,
				"DoesCameraFade:d":	1,
				"LightChannels:d":	1,
				"ObjectFlags:d":	436,
				"ScriptResource:s":	"",
				"InitialPos:fff":	[-6091.5615234375, -1695.866943359375, -16607.52734375],
				"Orientation:fff":	[0, 0, 0],
				"LocalBoundingBox:ffffff":	[-405.28741455078125, -307.69247436523437, -135.33395385742187, 405.28741455078125, 307.69247436523437, 135.33395385742187],
				"ObjSaveFlag:d":	0,
				"ObjName:s":	"RB_Alert_Vol",
				"Name:s":	"RB_Alert_Vol",
				"Pos:fff":	[-6091.5615234375, -1695.866943359375, -16607.52734375],
				"BBox:ffffff":	[-6496.84912109375, -2003.5594482421875, -16742.861328125, -5686.27392578125, -1388.1744384765625, -16472.193359375],
				"Orient:fff":	[0, 0, 0],
				"HalfDimensions:fff":	[405.28741455078125, 307.69247436523437, 135.33395385742187],
				"Pain:s":	"none"
			}]
	}, {
		"name":	"Volume",
		"row_count":	1,
		"rows":	[{
				"GUID:s":	"0D8ADA4B_46E10001",
				"DoesCameraColl:d":	1,
				"DoesCameraFade:d":	1,
				"LightChannels:d":	1,
				"ObjectFlags:d":	436,
				"ScriptResource:s":	"",
				"InitialPos:fff":	[-6364.4736328125, -1870.034912109375, -14600.0654296875],
				"Orientation:fff":	[0, 0, 0],
				"LocalBoundingBox:ffffff":	[-8.1057615280151367, -307.69247436523437, -3.6296501159667969, 8.1057615280151367, 307.69247436523437, 3.6296501159667969],
				"ObjSaveFlag:d":	0,
				"ObjName:s":	"RB_Run_Vol 005",
				"Name:s":	"RB_Run_Vol 005",
				"Pos:fff":	[-6364.4736328125, -1870.034912109375, -14600.0654296875],
				"BBox:ffffff":	[-6372.57958984375, -2177.727294921875, -14603.6953125, -6356.36767578125, -1562.3424072265625, -14596.435546875],
				"Orient:fff":	[0, 0, 0],
				"HalfDimensions:fff":	[8.1057615280151367, 307.69247436523437, 3.6296501159667969],
				"Pain:s":	"none"
			}]
	}, {
		"name":	"Volume",
		"row_count":	1,
		"rows":	[{
				"GUID:s":	"CD5884D2_5965F800",
				"DoesCameraColl:d":	1,
				"DoesCameraFade:d":	1,
				"LightChannels:d":	1,
				"ObjectFlags:d":	432,
				"ScriptResource:s":	"",
				"InitialPos:fff":	[-4952.6162109375, -1073.2379150390625, -10680.326171875],
				"Orientation:fff":	[0, 35.100025177001953, 0],
				"LocalBoundingBox:ffffff":	[-261.8404541015625, -484.78500366210937, -343.10580444335937, 261.8404541015625, 484.78500366210937, 343.10580444335937],
				"ObjSaveFlag:d":	0,
				"ObjName:s":	"Rope Jump Tutorial Vol",
				"Name:s":	"Rope Jump Tutorial Vol",
				"Pos:fff":	[-4952.6162109375, -1073.2379150390625, -10680.326171875],
				"BBox:ffffff":	[-5214.45654296875, -1558.02294921875, -11023.431640625, -4690.77587890625, -588.452880859375, -10337.220703125],
				"Orient:fff":	[0, 35.100025177001953, 0],
				"HalfDimensions:fff":	[50, 484.78500366210937, 384.22750854492187],
				"Pain:s":	"none"
			}]
	}, {
		"name":	"Volume",
		"row_count":	1,
		"rows":	[{
				"GUID:s":	"0D8AD04C_BDB9A000",
				"DoesCameraColl:d":	1,
				"DoesCameraFade:d":	1,
				"LightChannels:d":	1,
				"ObjectFlags:d":	432,
				"ScriptResource:s":	"",
				"InitialPos:fff":	[-15746.57421875, 865.76708984375, -5860.63427734375],
				"Orientation:fff":	[0, 25.649999618530273, 0],
				"LocalBoundingBox:ffffff":	[-66.7163848876953, -50, -66.7163848876953, 66.7163848876953, 50, 66.7163848876953],
				"ObjSaveFlag:d":	0,
				"ObjName:s":	"Spider GoTo Vol 001",
				"Name:s":	"Spider GoTo Vol 001",
				"Pos:fff":	[-15746.57421875, 865.76708984375, -5860.63427734375],
				"BBox:ffffff":	[-15813.291015625, 815.76708984375, -5927.3505859375, -15679.857421875, 915.76708984375, -5793.91796875],
				"Orient:fff":	[0, 25.649999618530273, 0],
				"HalfDimensions:fff":	[50, 50, 50],
				"Pain:s":	"none"
			}]
	}, {
		"name":	"Volume",
		"row_count":	1,
		"rows":	[{
				"GUID:s":	"0D8AD04C_BDBA8401",
				"DoesCameraColl:d":	1,
				"DoesCameraFade:d":	1,
				"LightChannels:d":	1,
				"ObjectFlags:d":	432,
				"ScriptResource:s":	"",
				"InitialPos:fff":	[-15970.087890625, 1045.2288818359375, -6226.205078125],
				"Orientation:fff":	[0, 25.649999618530273, 0],
				"LocalBoundingBox:ffffff":	[-66.7163848876953, -50, -66.7163848876953, 66.7163848876953, 50, 66.7163848876953],
				"ObjSaveFlag:d":	0,
				"ObjName:s":	"Spider GoTo Vol 002",
				"Name:s":	"Spider GoTo Vol 002",
				"Pos:fff":	[-15970.087890625, 1045.2288818359375, -6226.205078125],
				"BBox:ffffff":	[-16036.8046875, 995.2288818359375, -6292.92138671875, -15903.37109375, 1095.2288818359375, -6159.48876953125],
				"Orient:fff":	[0, 25.649999618530273, 0],
				"HalfDimensions:fff":	[50, 50, 50],
				"Pain:s":	"none"
			}]
	}, {
		"name":	"Volume",
		"row_count":	1,
		"rows":	[{
				"GUID:s":	"0D8AD10D_E60E1C01",
				"DoesCameraColl:d":	1,
				"DoesCameraFade:d":	1,
				"LightChannels:d":	1,
				"ObjectFlags:d":	432,
				"ScriptResource:s":	"",
				"InitialPos:fff":	[-16290.7783203125, 650.1363525390625, -6062.013671875],
				"Orientation:fff":	[0, 0, 0],
				"LocalBoundingBox:ffffff":	[-50, -50, -50, 50, 50, 50],
				"ObjSaveFlag:d":	0,
				"ObjName:s":	"Spider SpawnFaceVol",
				"Name:s":	"Spider SpawnFaceVol",
				"Pos:fff":	[-16290.7783203125, 650.1363525390625, -6062.013671875],
				"BBox:ffffff":	[-16340.7783203125, 600.1363525390625, -6112.013671875, -16240.7783203125, 700.1363525390625, -6012.013671875],
				"Orient:fff":	[0, 0, 0],
				"HalfDimensions:fff":	[50, 50, 50],
				"Pain:s":	"none"
			}]
	}, {
		"name":	"Volume",
		"row_count":	1,
		"rows":	[{
				"GUID:s":	"0D8AD10D_E60EEC00",
				"DoesCameraColl:d":	1,
				"DoesCameraFade:d":	1,
				"LightChannels:d":	1,
				"ObjectFlags:d":	432,
				"ScriptResource:s":	"",
				"InitialPos:fff":	[-15904.9462890625, 614.8653564453125, -7049.59619140625],
				"Orientation:fff":	[0, 0, 0],
				"LocalBoundingBox:ffffff":	[-111.50003814697266, -239.49995422363281, -308.87994384765625, 111.50003814697266, 239.49995422363281, 308.87994384765625],
				"ObjSaveFlag:d":	0,
				"ObjName:s":	"Spider SpawnTrigVol",
				"Name:s":	"Spider SpawnTrigVol",
				"Pos:fff":	[-15904.9462890625, 614.8653564453125, -7049.59619140625],
				"BBox:ffffff":	[-16016.4462890625, 375.36541748046875, -7358.47607421875, -15793.4462890625, 854.36529541015625, -6740.71630859375],
				"Orient:fff":	[0, 0, 0],
				"HalfDimensions:fff":	[111.50003814697266, 239.49995422363281, 308.87994384765625],
				"Pain:s":	"none"
			}]
	}, {
		"name":	"Volume",
		"row_count":	1,
		"rows":	[{
				"GUID:s":	"0D8AD10D_E60D8400",
				"DoesCameraColl:d":	1,
				"DoesCameraFade:d":	1,
				"LightChannels:d":	1,
				"ObjectFlags:d":	432,
				"ScriptResource:s":	"",
				"InitialPos:fff":	[-16382.5029296875, 650.50848388671875, -5698.3837890625],
				"Orientation:fff":	[0, 0, 0],
				"LocalBoundingBox:ffffff":	[-50, -50, -50, 50, 50, 50],
				"ObjSaveFlag:d":	0,
				"ObjName:s":	"Spider SpawnVol",
				"Name:s":	"Spider SpawnVol",
				"Pos:fff":	[-16382.5029296875, 650.50848388671875, -5698.3837890625],
				"BBox:ffffff":	[-16432.50390625, 600.50848388671875, -5748.3837890625, -16332.5029296875, 700.50848388671875, -5648.3837890625],
				"Orient:fff":	[0, 0, 0],
				"HalfDimensions:fff":	[50, 50, 50],
				"Pain:s":	"none"
			}]
	}, {
		"name":	"Volume",
		"row_count":	1,
		"rows":	[{
				"GUID:s":	"CD588B10_39CD8C00",
				"DoesCameraColl:d":	1,
				"DoesCameraFade:d":	1,
				"LightChannels:d":	1,
				"ObjectFlags:d":	432,
				"ScriptResource:s":	"",
				"InitialPos:fff":	[-6706.56982421875, -566.6651611328125, -11642.716796875],
				"Orientation:fff":	[0, 10.80002498626709, 0],
				"LocalBoundingBox:ffffff":	[-257.30230712890625, -167.67999267578125, -76.5328826904297, 257.30230712890625, 167.67999267578125, 76.5328826904297],
				"ObjSaveFlag:d":	0,
				"ObjName:s":	"Spike Trap Vol 001",
				"Name:s":	"Spike Trap Vol 001",
				"Pos:fff":	[-6706.56982421875, -566.6651611328125, -11642.716796875],
				"BBox:ffffff":	[-6963.8720703125, -734.34515380859375, -11719.25, -6449.267578125, -398.98516845703125, -11566.18359375],
				"Orient:fff":	[0, 10.80002498626709, 0],
				"HalfDimensions:fff":	[256.40997314453125, 167.67999267578125, 29.000003814697266],
				"Pain:s":	"none"
			}]
	}, {
		"name":	"Volume",
		"row_count":	1,
		"rows":	[{
				"GUID:s":	"CD588B10_39CF1801",
				"DoesCameraColl:d":	1,
				"DoesCameraFade:d":	1,
				"LightChannels:d":	1,
				"ObjectFlags:d":	432,
				"ScriptResource:s":	"",
				"InitialPos:fff":	[-6920.7119140625, -591.48956298828125, -11876.814453125],
				"Orientation:fff":	[0, 12.149970054626465, 0],
				"LocalBoundingBox:ffffff":	[-367.0633544921875, -158.51002502441406, -106.06279754638672, 367.0633544921875, 158.51002502441406, 106.06279754638672],
				"ObjSaveFlag:d":	0,
				"ObjName:s":	"Spike Trap Vol 002",
				"Name:s":	"Spike Trap Vol 002",
				"Pos:fff":	[-6920.7119140625, -591.48956298828125, -11876.814453125],
				"BBox:ffffff":	[-7287.775390625, -749.99957275390625, -11982.876953125, -6553.6484375, -432.97955322265625, -11770.751953125],
				"Orient:fff":	[0, 12.149970054626465, 0],
				"HalfDimensions:fff":	[369.23043823242187, 158.51002502441406, 29.000003814697266],
				"Pain:s":	"none"
			}]
	}, {
		"name":	"Volume",
		"row_count":	1,
		"rows":	[{
				"GUID:s":	"CD588B10_39D3BC01",
				"DoesCameraColl:d":	1,
				"DoesCameraFade:d":	1,
				"LightChannels:d":	1,
				"ObjectFlags:d":	432,
				"ScriptResource:s":	"",
				"InitialPos:fff":	[1086.5361328125, -1257.9434814453125, -10748.3388671875],
				"Orientation:fff":	[0, 20.699989318847656, 0],
				"LocalBoundingBox:ffffff":	[-386.730712890625, -262.52410888671875, -169.38772583007812, 386.730712890625, 262.52410888671875, 169.38772583007812],
				"ObjSaveFlag:d":	0,
				"ObjName:s":	"Spike Trap Vol 004",
				"Name:s":	"Spike Trap Vol 004",
				"Pos:fff":	[1086.5361328125, -1257.9434814453125, -10748.3388671875],
				"BBox:ffffff":	[699.805419921875, -1520.467529296875, -10917.7265625, 1473.266845703125, -995.41937255859375, -10578.951171875],
				"Orient:fff":	[0, 20.699989318847656, 0],
				"HalfDimensions:fff":	[402.461181640625, 262.52410888671875, 29.000003814697266],
				"Pain:s":	"none"
			}]
	}, {
		"name":	"Volume",
		"row_count":	1,
		"rows":	[{
				"GUID:s":	"CD588B10_39D53801",
				"DoesCameraColl:d":	1,
				"DoesCameraFade:d":	1,
				"LightChannels:d":	1,
				"ObjectFlags:d":	432,
				"ScriptResource:s":	"",
				"InitialPos:fff":	[1291.9559326171875, -1228.0960693359375, -10404.4462890625],
				"Orientation:fff":	[0, 17.999984741210937, 0],
				"LocalBoundingBox:ffffff":	[-391.724853515625, -262.52410888671875, -151.94789123535156, 391.724853515625, 262.52410888671875, 151.94789123535156],
				"ObjSaveFlag:d":	0,
				"ObjName:s":	"Spike Trap Vol 005",
				"Name:s":	"Spike Trap Vol 005",
				"Pos:fff":	[1291.9559326171875, -1228.0960693359375, -10404.4462890625],
				"BBox:ffffff":	[900.2310791015625, -1490.6201171875, -10556.39453125, 1683.6807861328125, -965.57196044921875, -10252.498046875],
				"Orient:fff":	[0, 17.999984741210937, 0],
				"HalfDimensions:fff":	[402.461181640625, 262.52410888671875, 29.000003814697266],
				"Pain:s":	"none"
			}]
	}, {
		"name":	"Volume",
		"row_count":	1,
		"rows":	[{
				"GUID:s":	"CD588B10_39D5F801",
				"DoesCameraColl:d":	1,
				"DoesCameraFade:d":	1,
				"LightChannels:d":	1,
				"ObjectFlags:d":	432,
				"ScriptResource:s":	"",
				"InitialPos:fff":	[-5957.32177734375, -426.19754028320312, -3279.93994140625],
				"Orientation:fff":	[0, 3.6000080108642578, 0],
				"LocalBoundingBox:ffffff":	[-403.48794555664062, -262.52410888671875, -54.213584899902344, 403.48794555664062, 262.52410888671875, 54.213584899902344],
				"ObjSaveFlag:d":	0,
				"ObjName:s":	"Spike Trap Vol 006",
				"Name:s":	"Spike Trap Vol 006",
				"Pos:fff":	[-5957.32177734375, -426.19754028320312, -3279.93994140625],
				"BBox:ffffff":	[-6360.8095703125, -688.7216796875, -3334.153564453125, -5553.833984375, -163.67343139648437, -3225.726318359375],
				"Orient:fff":	[0, 3.6000080108642578, 0],
				"HalfDimensions:fff":	[402.461181640625, 262.52410888671875, 29.000003814697266],
				"Pain:s":	"none"
			}]
	}, {
		"name":	"Volume",
		"row_count":	1,
		"rows":	[{
				"GUID:s":	"CD588B10_39D6C001",
				"DoesCameraColl:d":	1,
				"DoesCameraFade:d":	1,
				"LightChannels:d":	1,
				"ObjectFlags:d":	432,
				"ScriptResource:s":	"",
				"InitialPos:fff":	[-5177.130859375, -43.879730224609375, -6734.52294921875],
				"Orientation:fff":	[0, 14.849976539611816, 0],
				"LocalBoundingBox:ffffff":	[-396.451416015625, -262.52410888671875, -131.17778015136719, 396.451416015625, 262.52410888671875, 131.17778015136719],
				"ObjSaveFlag:d":	0,
				"ObjName:s":	"Spike Trap Vol 007",
				"Name:s":	"Spike Trap Vol 007",
				"Pos:fff":	[-5177.130859375, -43.879730224609375, -6734.52294921875],
				"BBox:ffffff":	[-5573.58203125, -306.40383911132812, -6865.70068359375, -4780.6796875, 218.64437866210937, -6603.34521484375],
				"Orient:fff":	[0, 14.849976539611816, 0],
				"HalfDimensions:fff":	[402.461181640625, 262.52410888671875, 29.000003814697266],
				"Pain:s":	"none"
			}]
	}, {
		"name":	"Volume",
		"row_count":	1,
		"rows":	[{
				"GUID:s":	"CD588B10_39DA6C01",
				"DoesCameraColl:d":	1,
				"DoesCameraFade:d":	1,
				"LightChannels:d":	1,
				"ObjectFlags:d":	432,
				"ScriptResource:s":	"",
				"InitialPos:fff":	[-8183.5615234375, 409.24188232421875, -10841.6572265625],
				"Orientation:fff":	[0, 88.650032043457031, 0],
				"LocalBoundingBox:ffffff":	[-38.473594665527344, -180.66908264160156, -403.03268432617187, 38.473594665527344, 180.66908264160156, 403.03268432617187],
				"ObjSaveFlag:d":	0,
				"ObjName:s":	"Spike Trap Vol 008",
				"Name:s":	"Spike Trap Vol 008",
				"Pos:fff":	[-8183.5615234375, 409.24188232421875, -10841.6572265625],
				"BBox:ffffff":	[-8222.03515625, 228.57279968261719, -11244.689453125, -8145.087890625, 589.91094970703125, -10438.625],
				"Orient:fff":	[0, 88.650032043457031, 0],
				"HalfDimensions:fff":	[402.461181640625, 180.66908264160156, 29.000003814697266],
				"Pain:s":	"none"
			}]
	}, {
		"name":	"Volume",
		"row_count":	1,
		"rows":	[{
				"GUID:s":	"CD588B10_39DC4801",
				"DoesCameraColl:d":	1,
				"DoesCameraFade:d":	1,
				"LightChannels:d":	1,
				"ObjectFlags:d":	432,
				"ScriptResource:s":	"",
				"InitialPos:fff":	[-8361.3427734375, 385.88461303710937, -10845.337890625],
				"Orientation:fff":	[0, 90.450035095214844, 0],
				"LocalBoundingBox:ffffff":	[-32.160259246826172, -180.66908264160156, -402.67654418945312, 32.160259246826172, 180.66908264160156, 402.67654418945312],
				"ObjSaveFlag:d":	0,
				"ObjName:s":	"Spike Trap Vol 009",
				"Name:s":	"Spike Trap Vol 009",
				"Pos:fff":	[-8361.3427734375, 385.88461303710937, -10845.337890625],
				"BBox:ffffff":	[-8393.5029296875, 205.21553039550781, -11248.0146484375, -8329.1826171875, 566.5537109375, -10442.6611328125],
				"Orient:fff":	[0, 90.450035095214844, 0],
				"HalfDimensions:fff":	[402.461181640625, 180.66908264160156, 29.000003814697266],
				"Pain:s":	"none"
			}]
	}, {
		"name":	"Volume",
		"row_count":	1,
		"rows":	[{
				"GUID:s":	"CD588B10_39DDBC01",
				"DoesCameraColl:d":	1,
				"DoesCameraFade:d":	1,
				"LightChannels:d":	1,
				"ObjectFlags:d":	432,
				"ScriptResource:s":	"",
				"InitialPos:fff":	[-8547.3486328125, 410.55130004882812, -10851.2978515625],
				"Orientation:fff":	[0, 88.200035095214844, 0],
				"LocalBoundingBox:ffffff":	[-41.6270523071289, -180.66908264160156, -403.17349243164062, 41.6270523071289, 180.66908264160156, 403.17349243164062],
				"ObjSaveFlag:d":	0,
				"ObjName:s":	"Spike Trap Vol 011",
				"Name:s":	"Spike Trap Vol 011",
				"Pos:fff":	[-8547.3486328125, 410.55130004882812, -10851.2978515625],
				"BBox:ffffff":	[-8588.9755859375, 229.88221740722656, -11254.4716796875, -8505.7216796875, 591.22039794921875, -10448.1240234375],
				"Orient:fff":	[0, 88.200035095214844, 0],
				"HalfDimensions:fff":	[402.461181640625, 180.66908264160156, 29.000003814697266],
				"Pain:s":	"none"
			}]
	}, {
		"name":	"Volume",
		"row_count":	1,
		"rows":	[{
				"GUID:s":	"CD588B10_39FC0C01",
				"DoesCameraColl:d":	1,
				"DoesCameraFade:d":	1,
				"LightChannels:d":	1,
				"ObjectFlags:d":	432,
				"ScriptResource:s":	"",
				"InitialPos:fff":	[-7760.94580078125, 954.72393798828125, -9560.001953125],
				"Orientation:fff":	[0, -164.24996948242187, 0],
				"LocalBoundingBox:ffffff":	[-395.22262573242187, -180.66908264160156, -137.15556335449219, 395.22262573242187, 180.66908264160156, 137.15556335449219],
				"ObjSaveFlag:d":	0,
				"ObjName:s":	"Spike Trap Vol 012",
				"Name:s":	"Spike Trap Vol 012",
				"Pos:fff":	[-7760.94580078125, 954.72393798828125, -9560.001953125],
				"BBox:ffffff":	[-8156.16845703125, 774.05487060546875, -9697.1572265625, -7365.72314453125, 1135.39306640625, -9422.8466796875],
				"Orient:fff":	[0, -164.24996948242187, 0],
				"HalfDimensions:fff":	[402.461181640625, 180.66908264160156, 29.000003814697266],
				"Pain:s":	"none"
			}]
	}, {
		"name":	"Volume",
		"row_count":	1,
		"rows":	[{
				"GUID:s":	"CD588B10_39FD4001",
				"DoesCameraColl:d":	1,
				"DoesCameraFade:d":	1,
				"LightChannels:d":	1,
				"ObjectFlags:d":	432,
				"ScriptResource:s":	"",
				"InitialPos:fff":	[-7713.0302734375, 954.72406005859375, -9271.64453125],
				"Orientation:fff":	[0, -174.59994506835937, 0],
				"LocalBoundingBox:ffffff":	[-403.4041748046875, -180.66908264160156, -66.7466049194336, 403.4041748046875, 180.66908264160156, 66.7466049194336],
				"ObjSaveFlag:d":	0,
				"ObjName:s":	"Spike Trap Vol 013",
				"Name:s":	"Spike Trap Vol 013",
				"Pos:fff":	[-7713.0302734375, 954.72406005859375, -9271.64453125],
				"BBox:ffffff":	[-8116.4345703125, 774.05499267578125, -9338.3916015625, -7309.6259765625, 1135.3931884765625, -9204.8974609375],
				"Orient:fff":	[0, -174.59994506835937, 0],
				"HalfDimensions:fff":	[402.461181640625, 180.66908264160156, 29.000003814697266],
				"Pain:s":	"none"
			}]
	}, {
		"name":	"Volume",
		"row_count":	1,
		"rows":	[{
				"GUID:s":	"CD588CD2_5EE9F400",
				"DoesCameraColl:d":	1,
				"DoesCameraFade:d":	1,
				"LightChannels:d":	1,
				"ObjectFlags:d":	432,
				"ScriptResource:s":	"",
				"InitialPos:fff":	[-9012.626953125, 439.32293701171875, -8914.1328125],
				"Orientation:fff":	[0, -19.799989700317383, 0],
				"LocalBoundingBox:ffffff":	[-316.82672119140625, -197.35075378417969, -155.01095581054687, 316.82672119140625, 197.35075378417969, 155.01095581054687],
				"ObjSaveFlag:d":	0,
				"ObjName:s":	"View Troll Hole Key Vol",
				"Name:s":	"View Troll Hole Key Vol",
				"Pos:fff":	[-9012.626953125, 439.32293701171875, -8914.1328125],
				"BBox:ffffff":	[-9329.4541015625, 241.97218322753906, -9069.1435546875, -8695.7998046875, 636.6737060546875, -8759.1220703125],
				"Orient:fff":	[0, -19.799989700317383, 0],
				"HalfDimensions:fff":	[318.73306274414062, 197.35075378417969, 50],
				"Pain:s":	"none"
			}]
	}, {
		"name":	"Volume",
		"row_count":	1,
		"rows":	[{
				"GUID:s":	"CD588910_EC283000",
				"DoesCameraColl:d":	1,
				"DoesCameraFade:d":	1,
				"LightChannels:d":	1,
				"ObjectFlags:d":	432,
				"ScriptResource:s":	"",
				"InitialPos:fff":	[-7789.9755859375, 1053.5994873046875, -9492.8291015625],
				"Orientation:fff":	[0, 15.749978065490723, 0],
				"LocalBoundingBox:ffffff":	[-342.19268798828125, -361.80502319335938, -140.80325317382812, 342.19268798828125, 361.80502319335938, 140.80325317382812],
				"ObjSaveFlag:d":	0,
				"ObjName:s":	"Vine Lower Trigger 001",
				"Name:s":	"Vine Lower Trigger 001",
				"Pos:fff":	[-7789.9755859375, 1053.5994873046875, -9492.8291015625],
				"BBox:ffffff":	[-8132.16845703125, 691.79443359375, -9633.6328125, -7447.78271484375, 1415.404541015625, -9352.025390625],
				"Orient:fff":	[0, 15.749978065490723, 0],
				"HalfDimensions:fff":	[341.43994140625, 361.80502319335938, 50],
				"Pain:s":	"none"
			}]
	}]