[{
		"name":	"Light",
		"row_count":	1,
		"rows":	[{
				"GUID:s":	"B5D7AA89_E0891001",
				"Name:s":	"ent_Point_056",
				"Kind:d":	1,
				"Color:dddd":	[102, 206, 255, 255],
				"Intensity:f":	2,
				"Pos:fff":	[-1642.8785400390625, 368.53488159179687, -761.43115234375],
				"FlickerAmp:f":	15,
				"FlickerJitter:f":	5,
				"FlickerSpeed:f":	10,
				"AttenStart:f":	0,
				"AttenEnd:f":	1000,
				"Dynamic:d":	0,
				"Flicker:d":	0,
				"TargetAttr:d":	7248,
				"LightChannel:d":	1
			}]
	}, {
		"name":	"Light",
		"row_count":	1,
		"rows":	[{
				"GUID:s":	"B5D7AA89_E0AA4001",
				"Name:s":	"ent_Point_057",
				"Kind:d":	1,
				"Color:dddd":	[255, 237, 166, 255],
				"Intensity:f":	1.2000000476837158,
				"Pos:fff":	[-4155.1875, 1283.7847900390625, 5621.48046875],
				"FlickerAmp:f":	15,
				"FlickerJitter:f":	5,
				"FlickerSpeed:f":	10,
				"AttenStart:f":	0,
				"AttenEnd:f":	300,
				"Dynamic:d":	0,
				"Flicker:d":	0,
				"TargetAttr:d":	7248,
				"LightChannel:d":	1
			}]
	}, {
		"name":	"Light",
		"row_count":	1,
		"rows":	[{
				"GUID:s":	"B5D7AA89_E0ACC801",
				"Name:s":	"ent_Point_058",
				"Kind:d":	1,
				"Color:dddd":	[136, 237, 255, 255],
				"Intensity:f":	1.5,
				"Pos:fff":	[-5499.267578125, 1535.21142578125, 5502.85498046875],
				"FlickerAmp:f":	15,
				"FlickerJitter:f":	5,
				"FlickerSpeed:f":	10,
				"AttenStart:f":	0,
				"AttenEnd:f":	400,
				"Dynamic:d":	0,
				"Flicker:d":	0,
				"TargetAttr:d":	7248,
				"LightChannel:d":	1
			}]
	}, {
		"name":	"Light",
		"row_count":	1,
		"rows":	[{
				"GUID:s":	"B5D7AA89_E0AE0001",
				"Name:s":	"ent_Point_059",
				"Kind:d":	1,
				"Color:dddd":	[255, 200, 114, 255],
				"Intensity:f":	1.5,
				"Pos:fff":	[-5681.63525390625, 1503.365966796875, 5949.88916015625],
				"FlickerAmp:f":	15,
				"FlickerJitter:f":	5,
				"FlickerSpeed:f":	10,
				"AttenStart:f":	0,
				"AttenEnd:f":	300,
				"Dynamic:d":	1,
				"Flicker:d":	2,
				"TargetAttr:d":	7248,
				"LightChannel:d":	1
			}]
	}, {
		"name":	"Light",
		"row_count":	1,
		"rows":	[{
				"GUID:s":	"B5D7A6C9_E4F30401",
				"Name:s":	"ent_Point_060",
				"Kind:d":	1,
				"Color:dddd":	[12, 255, 226, 255],
				"Intensity:f":	1.8999999761581421,
				"Pos:fff":	[-2459.177001953125, 608.16815185546875, 3229.9482421875],
				"FlickerAmp:f":	15,
				"FlickerJitter:f":	5,
				"FlickerSpeed:f":	10,
				"AttenStart:f":	0,
				"AttenEnd:f":	700,
				"Dynamic:d":	0,
				"Flicker:d":	0,
				"TargetAttr:d":	7248,
				"LightChannel:d":	1
			}]
	}, {
		"name":	"Light",
		"row_count":	1,
		"rows":	[{
				"GUID:s":	"B5D7A6C9_E4FBE001",
				"Name:s":	"ent_Point_061",
				"Kind:d":	1,
				"Color:dddd":	[7, 255, 238, 255],
				"Intensity:f":	1.8999999761581421,
				"Pos:fff":	[1549.981201171875, 1597.4642333984375, 3687.61767578125],
				"FlickerAmp:f":	15,
				"FlickerJitter:f":	5,
				"FlickerSpeed:f":	10,
				"AttenStart:f":	0,
				"AttenEnd:f":	350,
				"Dynamic:d":	0,
				"Flicker:d":	0,
				"TargetAttr:d":	7248,
				"LightChannel:d":	1
			}]
	}, {
		"name":	"Light",
		"row_count":	1,
		"rows":	[{
				"GUID:s":	"B5D7AD4E_8E43B401",
				"Name:s":	"ent_Point_063",
				"Kind:d":	1,
				"Color:dddd":	[9, 152, 255, 255],
				"Intensity:f":	2,
				"Pos:fff":	[-596.73114013671875, 372.13015747070312, 484.0374755859375],
				"FlickerAmp:f":	15,
				"FlickerJitter:f":	5,
				"FlickerSpeed:f":	10,
				"AttenStart:f":	0,
				"AttenEnd:f":	1000,
				"Dynamic:d":	0,
				"Flicker:d":	0,
				"TargetAttr:d":	7248,
				"LightChannel:d":	1
			}]
	}, {
		"name":	"Light",
		"row_count":	1,
		"rows":	[{
				"GUID:s":	"B5D7AC4E_92279401",
				"Name:s":	"ent_Point_065",
				"Kind:d":	1,
				"Color:dddd":	[70, 29, 255, 255],
				"Intensity:f":	2,
				"Pos:fff":	[-1700.3026123046875, 563.1390380859375, -1792.080078125],
				"FlickerAmp:f":	15,
				"FlickerJitter:f":	5,
				"FlickerSpeed:f":	10,
				"AttenStart:f":	0,
				"AttenEnd:f":	900,
				"Dynamic:d":	0,
				"Flicker:d":	0,
				"TargetAttr:d":	7248,
				"LightChannel:d":	1
			}]
	}, {
		"name":	"Light",
		"row_count":	1,
		"rows":	[{
				"GUID:s":	"B5D7A0CE_92CAAC01",
				"Name:s":	"ent_Point_066",
				"Kind:d":	1,
				"Color:dddd":	[45, 38, 255, 255],
				"Intensity:f":	2,
				"Pos:fff":	[-1462.4029541015625, 668.60845947265625, -2699.6181640625],
				"FlickerAmp:f":	15,
				"FlickerJitter:f":	5,
				"FlickerSpeed:f":	10,
				"AttenStart:f":	0,
				"AttenEnd:f":	900,
				"Dynamic:d":	0,
				"Flicker:d":	0,
				"TargetAttr:d":	7248,
				"LightChannel:d":	1
			}]
	}, {
		"name":	"Light",
		"row_count":	1,
		"rows":	[{
				"GUID:s":	"B5D7A0CE_92CB2401",
				"Name:s":	"ent_Point_067",
				"Kind:d":	1,
				"Color:dddd":	[58, 67, 255, 255],
				"Intensity:f":	2,
				"Pos:fff":	[-705.82147216796875, 652.4271240234375, -839.24884033203125],
				"FlickerAmp:f":	15,
				"FlickerJitter:f":	5,
				"FlickerSpeed:f":	10,
				"AttenStart:f":	0,
				"AttenEnd:f":	900,
				"Dynamic:d":	0,
				"Flicker:d":	0,
				"TargetAttr:d":	7248,
				"LightChannel:d":	1
			}]
	}, {
		"name":	"Light",
		"row_count":	1,
		"rows":	[{
				"GUID:s":	"B5D7A0CE_92CB7801",
				"Name:s":	"ent_Point_068",
				"Kind:d":	1,
				"Color:dddd":	[82, 70, 255, 255],
				"Intensity:f":	2,
				"Pos:fff":	[975.34783935546875, 498.41192626953125, 304.3079833984375],
				"FlickerAmp:f":	15,
				"FlickerJitter:f":	5,
				"FlickerSpeed:f":	10,
				"AttenStart:f":	0,
				"AttenEnd:f":	900,
				"Dynamic:d":	0,
				"Flicker:d":	0,
				"TargetAttr:d":	7248,
				"LightChannel:d":	1
			}]
	}, {
		"name":	"Light",
		"row_count":	1,
		"rows":	[{
				"GUID:s":	"B5D7A0CE_92CBA401",
				"Name:s":	"ent_Point_069",
				"Kind:d":	1,
				"Color:dddd":	[70, 61, 255, 255],
				"Intensity:f":	2,
				"Pos:fff":	[-249.23260498046875, 498.41192626953125, 14.938812255859375],
				"FlickerAmp:f":	15,
				"FlickerJitter:f":	5,
				"FlickerSpeed:f":	10,
				"AttenStart:f":	0,
				"AttenEnd:f":	900,
				"Dynamic:d":	0,
				"Flicker:d":	0,
				"TargetAttr:d":	7248,
				"LightChannel:d":	1
			}]
	}, {
		"name":	"Light",
		"row_count":	1,
		"rows":	[{
				"GUID:s":	"B5D7A0CE_92CCC801",
				"Name:s":	"ent_Point_070",
				"Kind:d":	1,
				"Color:dddd":	[98, 59, 255, 255],
				"Intensity:f":	2,
				"Pos:fff":	[-2385.724853515625, 652.4281005859375, -795.33233642578125],
				"FlickerAmp:f":	15,
				"FlickerJitter:f":	5,
				"FlickerSpeed:f":	10,
				"AttenStart:f":	0,
				"AttenEnd:f":	900,
				"Dynamic:d":	0,
				"Flicker:d":	0,
				"TargetAttr:d":	7248,
				"LightChannel:d":	1
			}]
	}, {
		"name":	"Light",
		"row_count":	1,
		"rows":	[{
				"GUID:s":	"B5D7A0CE_92CCEC01",
				"Name:s":	"ent_Point_071",
				"Kind:d":	1,
				"Color:dddd":	[100, 102, 255, 255],
				"Intensity:f":	2,
				"Pos:fff":	[-3617.541748046875, 406.6131591796875, 117.9632568359375],
				"FlickerAmp:f":	15,
				"FlickerJitter:f":	5,
				"FlickerSpeed:f":	10,
				"AttenStart:f":	0,
				"AttenEnd:f":	900,
				"Dynamic:d":	0,
				"Flicker:d":	0,
				"TargetAttr:d":	7248,
				"LightChannel:d":	1
			}]
	}, {
		"name":	"Light",
		"row_count":	1,
		"rows":	[{
				"GUID:s":	"B5D7A0CE_92CD4C01",
				"Name:s":	"ent_Point_072",
				"Kind:d":	1,
				"Color:dddd":	[73, 67, 255, 255],
				"Intensity:f":	2,
				"Pos:fff":	[-4538.556640625, 406.6131591796875, 285.6439208984375],
				"FlickerAmp:f":	15,
				"FlickerJitter:f":	5,
				"FlickerSpeed:f":	10,
				"AttenStart:f":	0,
				"AttenEnd:f":	900,
				"Dynamic:d":	0,
				"Flicker:d":	0,
				"TargetAttr:d":	7248,
				"LightChannel:d":	1
			}]
	}, {
		"name":	"Light",
		"row_count":	1,
		"rows":	[{
				"GUID:s":	"B5D7A0CE_935E3401",
				"Name:s":	"ent_Point_073",
				"Kind:d":	1,
				"Color:dddd":	[100, 102, 255, 255],
				"Intensity:f":	2,
				"Pos:fff":	[-2903.42919921875, 406.6129150390625, -157.20626831054687],
				"FlickerAmp:f":	15,
				"FlickerJitter:f":	5,
				"FlickerSpeed:f":	10,
				"AttenStart:f":	0,
				"AttenEnd:f":	900,
				"Dynamic:d":	0,
				"Flicker:d":	0,
				"TargetAttr:d":	7248,
				"LightChannel:d":	1
			}]
	}, {
		"name":	"Light",
		"row_count":	1,
		"rows":	[{
				"GUID:s":	"B5D7AD8E_9D0B9801",
				"Name:s":	"ent_Point_075",
				"Kind:d":	1,
				"Color:dddd":	[7, 255, 238, 255],
				"Intensity:f":	1.8999999761581421,
				"Pos:fff":	[1363.39013671875, 1491.939208984375, 4067.064208984375],
				"FlickerAmp:f":	15,
				"FlickerJitter:f":	5,
				"FlickerSpeed:f":	10,
				"AttenStart:f":	0,
				"AttenEnd:f":	350,
				"Dynamic:d":	0,
				"Flicker:d":	0,
				"TargetAttr:d":	7248,
				"LightChannel:d":	1
			}]
	}, {
		"name":	"Light",
		"row_count":	1,
		"rows":	[{
				"GUID:s":	"B5D7AC4E_9DBE4801",
				"Name:s":	"ent_Point_076",
				"Kind:d":	1,
				"Color:dddd":	[7, 255, 238, 255],
				"Intensity:f":	2,
				"Pos:fff":	[822.95556640625, 1259.3604736328125, 4163.7333984375],
				"FlickerAmp:f":	15,
				"FlickerJitter:f":	5,
				"FlickerSpeed:f":	10,
				"AttenStart:f":	0,
				"AttenEnd:f":	600,
				"Dynamic:d":	0,
				"Flicker:d":	0,
				"TargetAttr:d":	7248,
				"LightChannel:d":	1
			}]
	}, {
		"name":	"Light",
		"row_count":	1,
		"rows":	[{
				"GUID:s":	"B5D7AC4E_9DBEC801",
				"Name:s":	"ent_Point_077",
				"Kind:d":	1,
				"Color:dddd":	[7, 255, 238, 255],
				"Intensity:f":	2,
				"Pos:fff":	[496.71636962890625, 938.51171875, 3655.2138671875],
				"FlickerAmp:f":	15,
				"FlickerJitter:f":	5,
				"FlickerSpeed:f":	10,
				"AttenStart:f":	0,
				"AttenEnd:f":	450,
				"Dynamic:d":	0,
				"Flicker:d":	0,
				"TargetAttr:d":	7248,
				"LightChannel:d":	1
			}]
	}, {
		"name":	"Light",
		"row_count":	1,
		"rows":	[{
				"GUID:s":	"B5D7AC4E_9DBFC401",
				"Name:s":	"ent_Point_078",
				"Kind:d":	1,
				"Color:dddd":	[7, 255, 238, 255],
				"Intensity:f":	2,
				"Pos:fff":	[740.2425537109375, 1277.375244140625, 3613.151123046875],
				"FlickerAmp:f":	15,
				"FlickerJitter:f":	5,
				"FlickerSpeed:f":	10,
				"AttenStart:f":	0,
				"AttenEnd:f":	350,
				"Dynamic:d":	0,
				"Flicker:d":	0,
				"TargetAttr:d":	7248,
				"LightChannel:d":	1
			}]
	}, {
		"name":	"Light",
		"row_count":	1,
		"rows":	[{
				"GUID:s":	"B5D7AC4E_9DF3F801",
				"Name:s":	"ent_Point_079",
				"Kind:d":	1,
				"Color:dddd":	[7, 255, 238, 255],
				"Intensity:f":	2,
				"Pos:fff":	[106.29505920410156, -150.5484619140625, 961.5133056640625],
				"FlickerAmp:f":	15,
				"FlickerJitter:f":	5,
				"FlickerSpeed:f":	10,
				"AttenStart:f":	0,
				"AttenEnd:f":	360,
				"Dynamic:d":	0,
				"Flicker:d":	0,
				"TargetAttr:d":	7248,
				"LightChannel:d":	1
			}]
	}, {
		"name":	"Light",
		"row_count":	1,
		"rows":	[{
				"GUID:s":	"B5D7A8CE_9E099801",
				"Name:s":	"ent_Point_080",
				"Kind:d":	1,
				"Color:dddd":	[7, 255, 238, 255],
				"Intensity:f":	1.5,
				"Pos:fff":	[1029.06787109375, 380.0653076171875, 1143.3568115234375],
				"FlickerAmp:f":	15,
				"FlickerJitter:f":	5,
				"FlickerSpeed:f":	10,
				"AttenStart:f":	0,
				"AttenEnd:f":	450,
				"Dynamic:d":	0,
				"Flicker:d":	0,
				"TargetAttr:d":	7248,
				"LightChannel:d":	1
			}]
	}, {
		"name":	"Light",
		"row_count":	1,
		"rows":	[{
				"GUID:s":	"B5D7A8CE_9E0ABC01",
				"Name:s":	"ent_Point_081",
				"Kind:d":	1,
				"Color:dddd":	[7, 255, 238, 255],
				"Intensity:f":	1.5,
				"Pos:fff":	[1029.0679931640625, 992.3389892578125, 1143.3568115234375],
				"FlickerAmp:f":	15,
				"FlickerJitter:f":	5,
				"FlickerSpeed:f":	10,
				"AttenStart:f":	0,
				"AttenEnd:f":	450,
				"Dynamic:d":	0,
				"Flicker:d":	0,
				"TargetAttr:d":	7248,
				"LightChannel:d":	1
			}]
	}, {
		"name":	"Light",
		"row_count":	1,
		"rows":	[{
				"GUID:s":	"B5D7A8CE_9E0B0401",
				"Name:s":	"ent_Point_082",
				"Kind:d":	1,
				"Color:dddd":	[7, 255, 238, 255],
				"Intensity:f":	1.5,
				"Pos:fff":	[1111.3638916015625, 1684.614501953125, 1143.3568115234375],
				"FlickerAmp:f":	15,
				"FlickerJitter:f":	5,
				"FlickerSpeed:f":	10,
				"AttenStart:f":	0,
				"AttenEnd:f":	450,
				"Dynamic:d":	0,
				"Flicker:d":	0,
				"TargetAttr:d":	7248,
				"LightChannel:d":	1
			}]
	}, {
		"name":	"Light",
		"row_count":	1,
		"rows":	[{
				"GUID:s":	"B5D7AD4E_A8367001",
				"Name:s":	"ent_Point_083",
				"Kind:d":	1,
				"Color:dddd":	[136, 237, 255, 255],
				"Intensity:f":	1.5,
				"Pos:fff":	[-4801.533203125, 1484.955322265625, 5549.2958984375],
				"FlickerAmp:f":	15,
				"FlickerJitter:f":	5,
				"FlickerSpeed:f":	10,
				"AttenStart:f":	0,
				"AttenEnd:f":	250,
				"Dynamic:d":	0,
				"Flicker:d":	0,
				"TargetAttr:d":	7248,
				"LightChannel:d":	1
			}]
	}, {
		"name":	"Light",
		"row_count":	1,
		"rows":	[{
				"GUID:s":	"B5D7A88E_A8826401",
				"Name:s":	"ent_Point_084",
				"Kind:d":	1,
				"Color:dddd":	[7, 250, 255, 255],
				"Intensity:f":	1,
				"Pos:fff":	[-830.04925537109375, -87.3731918334961, 1237.7523193359375],
				"FlickerAmp:f":	15,
				"FlickerJitter:f":	5,
				"FlickerSpeed:f":	10,
				"AttenStart:f":	0,
				"AttenEnd:f":	300,
				"Dynamic:d":	0,
				"Flicker:d":	0,
				"TargetAttr:d":	7248,
				"LightChannel:d":	1
			}]
	}, {
		"name":	"Light",
		"row_count":	1,
		"rows":	[{
				"GUID:s":	"B5D7AD0E_A94B9401",
				"Name:s":	"ent_Point_085",
				"Kind:d":	1,
				"Color:dddd":	[220, 163, 15, 255],
				"Intensity:f":	2,
				"Pos:fff":	[-1714.1270751953125, 420.04568481445312, -2166.74951171875],
				"FlickerAmp:f":	15,
				"FlickerJitter:f":	5,
				"FlickerSpeed:f":	10,
				"AttenStart:f":	0,
				"AttenEnd:f":	400,
				"Dynamic:d":	0,
				"Flicker:d":	0,
				"TargetAttr:d":	7248,
				"LightChannel:d":	1
			}]
	}, {
		"name":	"Light",
		"row_count":	1,
		"rows":	[{
				"GUID:s":	"B5D7A509_3C665801",
				"Name:s":	"ent_Point_10",
				"Kind:d":	1,
				"Color:dddd":	[220, 163, 15, 255],
				"Intensity:f":	1.5,
				"Pos:fff":	[-1998.5164794921875, 949.0556640625, 5092.69287109375],
				"FlickerAmp:f":	15,
				"FlickerJitter:f":	5,
				"FlickerSpeed:f":	10,
				"AttenStart:f":	0,
				"AttenEnd:f":	1300,
				"Dynamic:d":	0,
				"Flicker:d":	0,
				"TargetAttr:d":	7248,
				"LightChannel:d":	1
			}]
	}, {
		"name":	"Light",
		"row_count":	1,
		"rows":	[{
				"GUID:s":	"B5D7AD89_3C6DDC01",
				"Name:s":	"ent_Point_11",
				"Kind:d":	1,
				"Color:dddd":	[14, 166, 255, 255],
				"Intensity:f":	1.5,
				"Pos:fff":	[-2566.411376953125, 1763.32470703125, 5200.07275390625],
				"FlickerAmp:f":	15,
				"FlickerJitter:f":	5,
				"FlickerSpeed:f":	10,
				"AttenStart:f":	0,
				"AttenEnd:f":	1000,
				"Dynamic:d":	0,
				"Flicker:d":	0,
				"TargetAttr:d":	7248,
				"LightChannel:d":	1
			}]
	}, {
		"name":	"Light",
		"row_count":	1,
		"rows":	[{
				"GUID:s":	"B5D7AD89_3C6EC801",
				"Name:s":	"ent_Point_12",
				"Kind:d":	1,
				"Color:dddd":	[255, 170, 2, 255],
				"Intensity:f":	1.4500000476837158,
				"Pos:fff":	[-1727.613525390625, 1726.3702392578125, 5744.080078125],
				"FlickerAmp:f":	15,
				"FlickerJitter:f":	5,
				"FlickerSpeed:f":	10,
				"AttenStart:f":	0,
				"AttenEnd:f":	700,
				"Dynamic:d":	0,
				"Flicker:d":	0,
				"TargetAttr:d":	7248,
				"LightChannel:d":	1
			}]
	}, {
		"name":	"Light",
		"row_count":	1,
		"rows":	[{
				"GUID:s":	"B5D7AD89_3C6F6001",
				"Name:s":	"ent_Point_13",
				"Kind:d":	1,
				"Color:dddd":	[8, 205, 255, 255],
				"Intensity:f":	1.5,
				"Pos:fff":	[-787.86016845703125, 1726.36962890625, 5002.908203125],
				"FlickerAmp:f":	15,
				"FlickerJitter:f":	5,
				"FlickerSpeed:f":	10,
				"AttenStart:f":	0,
				"AttenEnd:f":	1100,
				"Dynamic:d":	0,
				"Flicker:d":	0,
				"TargetAttr:d":	7248,
				"LightChannel:d":	1
			}]
	}, {
		"name":	"Light",
		"row_count":	1,
		"rows":	[{
				"GUID:s":	"B5D7AD89_3C703401",
				"Name:s":	"ent_Point_14",
				"Kind:d":	1,
				"Color:dddd":	[240, 174, 12, 255],
				"Intensity:f":	1.8999999761581421,
				"Pos:fff":	[95.7310791015625, 1118.004638671875, 3791.208984375],
				"FlickerAmp:f":	15,
				"FlickerJitter:f":	5,
				"FlickerSpeed:f":	10,
				"AttenStart:f":	0,
				"AttenEnd:f":	600,
				"Dynamic:d":	0,
				"Flicker:d":	0,
				"TargetAttr:d":	7248,
				"LightChannel:d":	1
			}]
	}, {
		"name":	"Light",
		"row_count":	1,
		"rows":	[{
				"GUID:s":	"B5D7AD89_3C715001",
				"Name:s":	"ent_Point_15",
				"Kind:d":	1,
				"Color:dddd":	[255, 192, 86, 255],
				"Intensity:f":	2,
				"Pos:fff":	[12.453338623046875, 744.24395751953125, 2746.60791015625],
				"FlickerAmp:f":	15,
				"FlickerJitter:f":	5,
				"FlickerSpeed:f":	10,
				"AttenStart:f":	0,
				"AttenEnd:f":	1000,
				"Dynamic:d":	0,
				"Flicker:d":	0,
				"TargetAttr:d":	7248,
				"LightChannel:d":	1
			}]
	}, {
		"name":	"Light",
		"row_count":	1,
		"rows":	[{
				"GUID:s":	"B5D7AD89_3C720C01",
				"Name:s":	"ent_Point_16",
				"Kind:d":	1,
				"Color:dddd":	[255, 163, 15, 255],
				"Intensity:f":	2,
				"Pos:fff":	[511.8524169921875, 1378.8310546875, 2375.684326171875],
				"FlickerAmp:f":	15,
				"FlickerJitter:f":	5,
				"FlickerSpeed:f":	10,
				"AttenStart:f":	0,
				"AttenEnd:f":	800,
				"Dynamic:d":	0,
				"Flicker:d":	0,
				"TargetAttr:d":	7248,
				"LightChannel:d":	1
			}]
	}, {
		"name":	"Light",
		"row_count":	1,
		"rows":	[{
				"GUID:s":	"B5D7AD89_3C72D801",
				"Name:s":	"ent_Point_17",
				"Kind:d":	1,
				"Color:dddd":	[20, 255, 240, 255],
				"Intensity:f":	1.9500000476837158,
				"Pos:fff":	[-333.36431884765625, 1378.8310546875, 1711.706787109375],
				"FlickerAmp:f":	15,
				"FlickerJitter:f":	5,
				"FlickerSpeed:f":	10,
				"AttenStart:f":	0,
				"AttenEnd:f":	1300,
				"Dynamic:d":	0,
				"Flicker:d":	0,
				"TargetAttr:d":	7248,
				"LightChannel:d":	1
			}]
	}, {
		"name":	"Light",
		"row_count":	1,
		"rows":	[{
				"GUID:s":	"B5D7AD89_3C736401",
				"Name:s":	"ent_Point_18",
				"Kind:d":	1,
				"Color:dddd":	[7, 237, 255, 255],
				"Intensity:f":	2.2000000476837158,
				"Pos:fff":	[-217.95587158203125, 678.26654052734375, 1655.918701171875],
				"FlickerAmp:f":	15,
				"FlickerJitter:f":	5,
				"FlickerSpeed:f":	10,
				"AttenStart:f":	0,
				"AttenEnd:f":	1600,
				"Dynamic:d":	0,
				"Flicker:d":	0,
				"TargetAttr:d":	7248,
				"LightChannel:d":	1
			}]
	}, {
		"name":	"Light",
		"row_count":	1,
		"rows":	[{
				"GUID:s":	"B5D7AD89_3C740801",
				"Name:s":	"ent_Point_19",
				"Kind:d":	1,
				"Color:dddd":	[255, 174, 12, 255],
				"Intensity:f":	2,
				"Pos:fff":	[-951.01416015625, 1299.0413818359375, 4156.78662109375],
				"FlickerAmp:f":	15,
				"FlickerJitter:f":	5,
				"FlickerSpeed:f":	10,
				"AttenStart:f":	0,
				"AttenEnd:f":	1100,
				"Dynamic:d":	0,
				"Flicker:d":	0,
				"TargetAttr:d":	7248,
				"LightChannel:d":	1
			}]
	}, {
		"name":	"Light",
		"row_count":	1,
		"rows":	[{
				"GUID:s":	"B5D7AA49_3C5AE401",
				"Name:s":	"ent_Point_2",
				"Kind:d":	1,
				"Color:dddd":	[220, 163, 15, 255],
				"Intensity:f":	2,
				"Pos:fff":	[-1611.2197265625, 372.13015747070312, 428.40945434570312],
				"FlickerAmp:f":	15,
				"FlickerJitter:f":	5,
				"FlickerSpeed:f":	10,
				"AttenStart:f":	0,
				"AttenEnd:f":	1500,
				"Dynamic:d":	0,
				"Flicker:d":	0,
				"TargetAttr:d":	7248,
				"LightChannel:d":	1
			}]
	}, {
		"name":	"Light",
		"row_count":	1,
		"rows":	[{
				"GUID:s":	"B5D7AD89_3C751801",
				"Name:s":	"ent_Point_20",
				"Kind:d":	1,
				"Color:dddd":	[255, 174, 12, 255],
				"Intensity:f":	2,
				"Pos:fff":	[-741.477294921875, 1743.029541015625, 4552.359375],
				"FlickerAmp:f":	15,
				"FlickerJitter:f":	5,
				"FlickerSpeed:f":	10,
				"AttenStart:f":	0,
				"AttenEnd:f":	900,
				"Dynamic:d":	0,
				"Flicker:d":	0,
				"TargetAttr:d":	7248,
				"LightChannel:d":	1
			}]
	}, {
		"name":	"Light",
		"row_count":	1,
		"rows":	[{
				"GUID:s":	"B5D7AD89_3C75E401",
				"Name:s":	"ent_Point_21",
				"Kind:d":	1,
				"Color:dddd":	[7, 255, 238, 255],
				"Intensity:f":	2.2000000476837158,
				"Pos:fff":	[192.5631103515625, 1798.8802490234375, 4950.017578125],
				"FlickerAmp:f":	15,
				"FlickerJitter:f":	5,
				"FlickerSpeed:f":	10,
				"AttenStart:f":	0,
				"AttenEnd:f":	900,
				"Dynamic:d":	0,
				"Flicker:d":	0,
				"TargetAttr:d":	7248,
				"LightChannel:d":	1
			}]
	}, {
		"name":	"Light",
		"row_count":	1,
		"rows":	[{
				"GUID:s":	"B5D7AD89_3C776C01",
				"Name:s":	"ent_Point_22",
				"Kind:d":	1,
				"Color:dddd":	[7, 255, 238, 255],
				"Intensity:f":	2,
				"Pos:fff":	[840.61431884765625, 1341.573486328125, 3155.660888671875],
				"FlickerAmp:f":	15,
				"FlickerJitter:f":	5,
				"FlickerSpeed:f":	10,
				"AttenStart:f":	0,
				"AttenEnd:f":	500,
				"Dynamic:d":	0,
				"Flicker:d":	0,
				"TargetAttr:d":	7248,
				"LightChannel:d":	1
			}]
	}, {
		"name":	"Light",
		"row_count":	1,
		"rows":	[{
				"GUID:s":	"B5D7AD89_3C787C01",
				"Name:s":	"ent_Point_23",
				"Kind:d":	1,
				"Color:dddd":	[7, 255, 238, 255],
				"Intensity:f":	1.5,
				"Pos:fff":	[741.354736328125, 837.23046875, 3034.2958984375],
				"FlickerAmp:f":	15,
				"FlickerJitter:f":	5,
				"FlickerSpeed:f":	10,
				"AttenStart:f":	0,
				"AttenEnd:f":	300,
				"Dynamic:d":	0,
				"Flicker:d":	0,
				"TargetAttr:d":	7248,
				"LightChannel:d":	1
			}]
	}, {
		"name":	"Light",
		"row_count":	1,
		"rows":	[{
				"GUID:s":	"B5D7AD89_3C7A3001",
				"Name:s":	"ent_Point_24",
				"Kind:d":	1,
				"Color:dddd":	[7, 255, 238, 255],
				"Intensity:f":	1,
				"Pos:fff":	[1094.843994140625, 1096.2359619140625, 2882.021240234375],
				"FlickerAmp:f":	15,
				"FlickerJitter:f":	5,
				"FlickerSpeed:f":	10,
				"AttenStart:f":	0,
				"AttenEnd:f":	600,
				"Dynamic:d":	0,
				"Flicker:d":	0,
				"TargetAttr:d":	7248,
				"LightChannel:d":	1
			}]
	}, {
		"name":	"Light",
		"row_count":	1,
		"rows":	[{
				"GUID:s":	"B5D7AD89_3C7BB001",
				"Name:s":	"ent_Point_25",
				"Kind:d":	1,
				"Color:dddd":	[14, 166, 255, 255],
				"Intensity:f":	2,
				"Pos:fff":	[908.9932861328125, 279.0704345703125, 2757.66455078125],
				"FlickerAmp:f":	15,
				"FlickerJitter:f":	5,
				"FlickerSpeed:f":	10,
				"AttenStart:f":	0,
				"AttenEnd:f":	600,
				"Dynamic:d":	0,
				"Flicker:d":	0,
				"TargetAttr:d":	7248,
				"LightChannel:d":	1
			}]
	}, {
		"name":	"Light",
		"row_count":	1,
		"rows":	[{
				"GUID:s":	"B5D7AD89_3C7D3001",
				"Name:s":	"ent_Point_26",
				"Kind:d":	1,
				"Color:dddd":	[11, 255, 169, 255],
				"Intensity:f":	2,
				"Pos:fff":	[828.5751953125, -9.87969970703125, 1130.7265625],
				"FlickerAmp:f":	15,
				"FlickerJitter:f":	5,
				"FlickerSpeed:f":	10,
				"AttenStart:f":	0,
				"AttenEnd:f":	700,
				"Dynamic:d":	0,
				"Flicker:d":	0,
				"TargetAttr:d":	7248,
				"LightChannel:d":	1
			}]
	}, {
		"name":	"Light",
		"row_count":	1,
		"rows":	[{
				"GUID:s":	"B5D7A509_3C8DA001",
				"Name:s":	"ent_Point_27",
				"Kind:d":	1,
				"Color:dddd":	[12, 255, 226, 255],
				"Intensity:f":	2,
				"Pos:fff":	[-1346.88818359375, 860.66790771484375, 2956.5185546875],
				"FlickerAmp:f":	15,
				"FlickerJitter:f":	5,
				"FlickerSpeed:f":	10,
				"AttenStart:f":	0,
				"AttenEnd:f":	1000,
				"Dynamic:d":	0,
				"Flicker:d":	0,
				"TargetAttr:d":	7248,
				"LightChannel:d":	1
			}]
	}, {
		"name":	"Light",
		"row_count":	1,
		"rows":	[{
				"GUID:s":	"B5D7A509_3C8E6001",
				"Name:s":	"ent_Point_28",
				"Kind:d":	1,
				"Color:dddd":	[255, 170, 2, 255],
				"Intensity:f":	2,
				"Pos:fff":	[-2990.894775390625, 909.12652587890625, 3131.07421875],
				"FlickerAmp:f":	15,
				"FlickerJitter:f":	5,
				"FlickerSpeed:f":	10,
				"AttenStart:f":	0,
				"AttenEnd:f":	800,
				"Dynamic:d":	0,
				"Flicker:d":	0,
				"TargetAttr:d":	7248,
				"LightChannel:d":	1
			}]
	}, {
		"name":	"Light",
		"row_count":	1,
		"rows":	[{
				"GUID:s":	"B5D7A509_3C8F1801",
				"Name:s":	"ent_Point_29",
				"Kind:d":	1,
				"Color:dddd":	[235, 170, 2, 255],
				"Intensity:f":	2,
				"Pos:fff":	[-2797.533203125, 1153.071533203125, 4110.6474609375],
				"FlickerAmp:f":	15,
				"FlickerJitter:f":	5,
				"FlickerSpeed:f":	10,
				"AttenStart:f":	0,
				"AttenEnd:f":	1000,
				"Dynamic:d":	0,
				"Flicker:d":	0,
				"TargetAttr:d":	7248,
				"LightChannel:d":	1
			}]
	}, {
		"name":	"Light",
		"row_count":	1,
		"rows":	[{
				"GUID:s":	"B5D7AA49_3C5B4C01",
				"Name:s":	"ent_Point_3",
				"Kind:d":	1,
				"Color:dddd":	[3, 187, 255, 255],
				"Intensity:f":	1.7000000476837158,
				"Pos:fff":	[-2967.8134765625, 300.7171630859375, 896.7169189453125],
				"FlickerAmp:f":	15,
				"FlickerJitter:f":	5,
				"FlickerSpeed:f":	10,
				"AttenStart:f":	0,
				"AttenEnd:f":	700,
				"Dynamic:d":	0,
				"Flicker:d":	0,
				"TargetAttr:d":	7248,
				"LightChannel:d":	1
			}]
	}, {
		"name":	"Light",
		"row_count":	1,
		"rows":	[{
				"GUID:s":	"B5D7A509_3C8FAC01",
				"Name:s":	"ent_Point_30",
				"Kind:d":	1,
				"Color:dddd":	[255, 170, 2, 255],
				"Intensity:f":	2,
				"Pos:fff":	[-3183.90087890625, 1624.540771484375, 3724.70654296875],
				"FlickerAmp:f":	15,
				"FlickerJitter:f":	5,
				"FlickerSpeed:f":	10,
				"AttenStart:f":	0,
				"AttenEnd:f":	900,
				"Dynamic:d":	0,
				"Flicker:d":	0,
				"TargetAttr:d":	7248,
				"LightChannel:d":	1
			}]
	}, {
		"name":	"Light",
		"row_count":	1,
		"rows":	[{
				"GUID:s":	"B5D7A509_3C905401",
				"Name:s":	"ent_Point_31",
				"Kind:d":	1,
				"Color:dddd":	[255, 170, 2, 255],
				"Intensity:f":	2,
				"Pos:fff":	[-2042.02294921875, 1755.6324462890625, 3963.568115234375],
				"FlickerAmp:f":	15,
				"FlickerJitter:f":	5,
				"FlickerSpeed:f":	10,
				"AttenStart:f":	0,
				"AttenEnd:f":	900,
				"Dynamic:d":	0,
				"Flicker:d":	0,
				"TargetAttr:d":	7248,
				"LightChannel:d":	1
			}]
	}, {
		"name":	"Light",
		"row_count":	1,
		"rows":	[{
				"GUID:s":	"B5D7A509_3C90D001",
				"Name:s":	"ent_Point_32",
				"Kind:d":	1,
				"Color:dddd":	[255, 170, 2, 255],
				"Intensity:f":	2,
				"Pos:fff":	[-3282.945556640625, 1172.0694580078125, 5002.28759765625],
				"FlickerAmp:f":	15,
				"FlickerJitter:f":	5,
				"FlickerSpeed:f":	10,
				"AttenStart:f":	0,
				"AttenEnd:f":	900,
				"Dynamic:d":	0,
				"Flicker:d":	0,
				"TargetAttr:d":	7248,
				"LightChannel:d":	1
			}]
	}, {
		"name":	"Light",
		"row_count":	1,
		"rows":	[{
				"GUID:s":	"B5D7A509_3C91C801",
				"Name:s":	"ent_Point_33",
				"Kind:d":	1,
				"Color:dddd":	[255, 170, 2, 255],
				"Intensity:f":	2,
				"Pos:fff":	[-3290.973876953125, 1591.70751953125, 4995.849609375],
				"FlickerAmp:f":	15,
				"FlickerJitter:f":	5,
				"FlickerSpeed:f":	10,
				"AttenStart:f":	0,
				"AttenEnd:f":	900,
				"Dynamic:d":	0,
				"Flicker:d":	0,
				"TargetAttr:d":	7248,
				"LightChannel:d":	1
			}]
	}, {
		"name":	"Light",
		"row_count":	1,
		"rows":	[{
				"GUID:s":	"B5D7A509_3C922401",
				"Name:s":	"ent_Point_34",
				"Kind:d":	1,
				"Color:dddd":	[4, 255, 217, 255],
				"Intensity:f":	2,
				"Pos:fff":	[-3232.314208984375, 1693.09130859375, 4298.36572265625],
				"FlickerAmp:f":	15,
				"FlickerJitter:f":	5,
				"FlickerSpeed:f":	10,
				"AttenStart:f":	0,
				"AttenEnd:f":	700,
				"Dynamic:d":	0,
				"Flicker:d":	0,
				"TargetAttr:d":	7248,
				"LightChannel:d":	1
			}]
	}, {
		"name":	"Light",
		"row_count":	1,
		"rows":	[{
				"GUID:s":	"B5D7A509_3C92BC01",
				"Name:s":	"ent_Point_35",
				"Kind:d":	1,
				"Color:dddd":	[4, 255, 217, 255],
				"Intensity:f":	2,
				"Pos:fff":	[-4064.241455078125, 942.482421875, 3942.357177734375],
				"FlickerAmp:f":	15,
				"FlickerJitter:f":	5,
				"FlickerSpeed:f":	10,
				"AttenStart:f":	0,
				"AttenEnd:f":	1000,
				"Dynamic:d":	0,
				"Flicker:d":	0,
				"TargetAttr:d":	7248,
				"LightChannel:d":	1
			}]
	}, {
		"name":	"Light",
		"row_count":	1,
		"rows":	[{
				"GUID:s":	"B5D7A509_3C93DC01",
				"Name:s":	"ent_Point_36",
				"Kind:d":	1,
				"Color:dddd":	[4, 255, 217, 255],
				"Intensity:f":	2,
				"Pos:fff":	[-3900.875732421875, 912.0338134765625, 4766.25927734375],
				"FlickerAmp:f":	15,
				"FlickerJitter:f":	5,
				"FlickerSpeed:f":	10,
				"AttenStart:f":	0,
				"AttenEnd:f":	800,
				"Dynamic:d":	0,
				"Flicker:d":	0,
				"TargetAttr:d":	7248,
				"LightChannel:d":	1
			}]
	}, {
		"name":	"Light",
		"row_count":	1,
		"rows":	[{
				"GUID:s":	"B5D7A509_3C953801",
				"Name:s":	"ent_Point_37",
				"Kind:d":	1,
				"Color:dddd":	[4, 255, 217, 255],
				"Intensity:f":	2,
				"Pos:fff":	[-3546.919189453125, 731.12359619140625, 4676.16845703125],
				"FlickerAmp:f":	15,
				"FlickerJitter:f":	5,
				"FlickerSpeed:f":	10,
				"AttenStart:f":	0,
				"AttenEnd:f":	900,
				"Dynamic:d":	0,
				"Flicker:d":	0,
				"TargetAttr:d":	7248,
				"LightChannel:d":	1
			}]
	}, {
		"name":	"Light",
		"row_count":	1,
		"rows":	[{
				"GUID:s":	"B5D7A509_3C96A401",
				"Name:s":	"ent_Point_38",
				"Kind:d":	1,
				"Color:dddd":	[4, 255, 217, 255],
				"Intensity:f":	2,
				"Pos:fff":	[-4187.21142578125, 1042.779296875, 2838.278076171875],
				"FlickerAmp:f":	15,
				"FlickerJitter:f":	5,
				"FlickerSpeed:f":	10,
				"AttenStart:f":	0,
				"AttenEnd:f":	900,
				"Dynamic:d":	0,
				"Flicker:d":	0,
				"TargetAttr:d":	7248,
				"LightChannel:d":	1
			}]
	}, {
		"name":	"Light",
		"row_count":	1,
		"rows":	[{
				"GUID:s":	"B5D7A509_3C974801",
				"Name:s":	"ent_Point_39",
				"Kind:d":	1,
				"Color:dddd":	[255, 170, 2, 255],
				"Intensity:f":	2,
				"Pos:fff":	[-3377.81689453125, 1176.26708984375, 2878.171875],
				"FlickerAmp:f":	15,
				"FlickerJitter:f":	5,
				"FlickerSpeed:f":	10,
				"AttenStart:f":	0,
				"AttenEnd:f":	700,
				"Dynamic:d":	0,
				"Flicker:d":	0,
				"TargetAttr:d":	7248,
				"LightChannel:d":	1
			}]
	}, {
		"name":	"Light",
		"row_count":	1,
		"rows":	[{
				"GUID:s":	"B5D7AA49_3C5CFC01",
				"Name:s":	"ent_Point_4",
				"Kind:d":	1,
				"Color:dddd":	[10, 108, 255, 255],
				"Intensity:f":	1.5,
				"Pos:fff":	[-4241.447265625, 300.71746826171875, 890.95574951171875],
				"FlickerAmp:f":	15,
				"FlickerJitter:f":	5,
				"FlickerSpeed:f":	10,
				"AttenStart:f":	0,
				"AttenEnd:f":	1100,
				"Dynamic:d":	0,
				"Flicker:d":	0,
				"TargetAttr:d":	7248,
				"LightChannel:d":	1
			}]
	}, {
		"name":	"Light",
		"row_count":	1,
		"rows":	[{
				"GUID:s":	"B5D7A509_3C981401",
				"Name:s":	"ent_Point_40",
				"Kind:d":	1,
				"Color:dddd":	[255, 170, 2, 255],
				"Intensity:f":	1.9500000476837158,
				"Pos:fff":	[-3358.32666015625, 1086.253662109375, 2137.33447265625],
				"FlickerAmp:f":	15,
				"FlickerJitter:f":	5,
				"FlickerSpeed:f":	10,
				"AttenStart:f":	0,
				"AttenEnd:f":	1000,
				"Dynamic:d":	0,
				"Flicker:d":	0,
				"TargetAttr:d":	7248,
				"LightChannel:d":	1
			}]
	}, {
		"name":	"Light",
		"row_count":	1,
		"rows":	[{
				"GUID:s":	"B5D7A509_3C989001",
				"Name:s":	"ent_Point_41",
				"Kind:d":	1,
				"Color:dddd":	[255, 170, 2, 255],
				"Intensity:f":	1.8999999761581421,
				"Pos:fff":	[-2962.771484375, 642.314453125, 2155.42626953125],
				"FlickerAmp:f":	15,
				"FlickerJitter:f":	5,
				"FlickerSpeed:f":	10,
				"AttenStart:f":	0,
				"AttenEnd:f":	900,
				"Dynamic:d":	0,
				"Flicker:d":	0,
				"TargetAttr:d":	7248,
				"LightChannel:d":	1
			}]
	}, {
		"name":	"Light",
		"row_count":	1,
		"rows":	[{
				"GUID:s":	"B5D7A509_3C998C01",
				"Name:s":	"ent_Point_42",
				"Kind:d":	1,
				"Color:dddd":	[1, 208, 255, 255],
				"Intensity:f":	2,
				"Pos:fff":	[-4115.6484375, 620.31805419921875, 2179.500732421875],
				"FlickerAmp:f":	15,
				"FlickerJitter:f":	5,
				"FlickerSpeed:f":	10,
				"AttenStart:f":	0,
				"AttenEnd:f":	1100,
				"Dynamic:d":	0,
				"Flicker:d":	0,
				"TargetAttr:d":	7248,
				"LightChannel:d":	1
			}]
	}, {
		"name":	"Light",
		"row_count":	1,
		"rows":	[{
				"GUID:s":	"B5D7A509_3C9C6C01",
				"Name:s":	"ent_Point_43",
				"Kind:d":	1,
				"Color:dddd":	[2, 255, 136, 255],
				"Intensity:f":	2,
				"Pos:fff":	[-4452.408203125, 482.74493408203125, 3079.314208984375],
				"FlickerAmp:f":	15,
				"FlickerJitter:f":	5,
				"FlickerSpeed:f":	10,
				"AttenStart:f":	0,
				"AttenEnd:f":	500,
				"Dynamic:d":	0,
				"Flicker:d":	0,
				"TargetAttr:d":	7248,
				"LightChannel:d":	1
			}]
	}, {
		"name":	"Light",
		"row_count":	1,
		"rows":	[{
				"GUID:s":	"B5D7A509_3C9D8401",
				"Name:s":	"ent_Point_44",
				"Kind:d":	1,
				"Color:dddd":	[2, 255, 136, 255],
				"Intensity:f":	1.5,
				"Pos:fff":	[-3427.427978515625, 230.50436401367188, 3577.681640625],
				"FlickerAmp:f":	15,
				"FlickerJitter:f":	5,
				"FlickerSpeed:f":	10,
				"AttenStart:f":	0,
				"AttenEnd:f":	500,
				"Dynamic:d":	0,
				"Flicker:d":	0,
				"TargetAttr:d":	7248,
				"LightChannel:d":	1
			}]
	}, {
		"name":	"Light",
		"row_count":	1,
		"rows":	[{
				"GUID:s":	"B5D7A0C9_3CA22801",
				"Name:s":	"ent_Point_45",
				"Kind:d":	1,
				"Color:dddd":	[7, 250, 255, 255],
				"Intensity:f":	1.5,
				"Pos:fff":	[-3814.2412109375, 230.50320434570312, 2698.9892578125],
				"FlickerAmp:f":	15,
				"FlickerJitter:f":	5,
				"FlickerSpeed:f":	10,
				"AttenStart:f":	0,
				"AttenEnd:f":	550,
				"Dynamic:d":	0,
				"Flicker:d":	0,
				"TargetAttr:d":	7248,
				"LightChannel:d":	1
			}]
	}, {
		"name":	"Light",
		"row_count":	1,
		"rows":	[{
				"GUID:s":	"B5D7A0C9_3CA34801",
				"Name:s":	"ent_Point_46",
				"Kind:d":	1,
				"Color:dddd":	[7, 250, 255, 255],
				"Intensity:f":	1.5,
				"Pos:fff":	[-4615.7880859375, 631.57501220703125, 1398.9410400390625],
				"FlickerAmp:f":	15,
				"FlickerJitter:f":	5,
				"FlickerSpeed:f":	10,
				"AttenStart:f":	0,
				"AttenEnd:f":	700,
				"Dynamic:d":	0,
				"Flicker:d":	0,
				"TargetAttr:d":	7248,
				"LightChannel:d":	1
			}]
	}, {
		"name":	"Light",
		"row_count":	1,
		"rows":	[{
				"GUID:s":	"B5D7A0C9_3CA3D401",
				"Name:s":	"ent_Point_47",
				"Kind:d":	1,
				"Color:dddd":	[7, 250, 255, 255],
				"Intensity:f":	1.2000000476837158,
				"Pos:fff":	[-4414.5146484375, 16.306365966796875, 1398.9410400390625],
				"FlickerAmp:f":	15,
				"FlickerJitter:f":	5,
				"FlickerSpeed:f":	10,
				"AttenStart:f":	0,
				"AttenEnd:f":	700,
				"Dynamic:d":	0,
				"Flicker:d":	0,
				"TargetAttr:d":	7248,
				"LightChannel:d":	1
			}]
	}, {
		"name":	"Light",
		"row_count":	1,
		"rows":	[{
				"GUID:s":	"B5D7A0C9_3CA43001",
				"Name:s":	"ent_Point_48",
				"Kind:d":	1,
				"Color:dddd":	[7, 250, 255, 255],
				"Intensity:f":	1,
				"Pos:fff":	[-3871.8212890625, -340.37777709960937, 1398.9410400390625],
				"FlickerAmp:f":	15,
				"FlickerJitter:f":	5,
				"FlickerSpeed:f":	10,
				"AttenStart:f":	0,
				"AttenEnd:f":	700,
				"Dynamic:d":	0,
				"Flicker:d":	0,
				"TargetAttr:d":	7248,
				"LightChannel:d":	1
			}]
	}, {
		"name":	"Light",
		"row_count":	1,
		"rows":	[{
				"GUID:s":	"B5D7A0C9_3CA50401",
				"Name:s":	"ent_Point_49",
				"Kind:d":	1,
				"Color:dddd":	[7, 250, 255, 255],
				"Intensity:f":	1,
				"Pos:fff":	[-2874.819580078125, -340.37716674804687, 1325.87255859375],
				"FlickerAmp:f":	15,
				"FlickerJitter:f":	5,
				"FlickerSpeed:f":	10,
				"AttenStart:f":	0,
				"AttenEnd:f":	600,
				"Dynamic:d":	0,
				"Flicker:d":	0,
				"TargetAttr:d":	7248,
				"LightChannel:d":	1
			}]
	}, {
		"name":	"Light",
		"row_count":	1,
		"rows":	[{
				"GUID:s":	"B5D7AA49_3C5DA401",
				"Name:s":	"ent_Point_5",
				"Kind:d":	1,
				"Color:dddd":	[220, 163, 15, 255],
				"Intensity:f":	1.2999999523162842,
				"Pos:fff":	[-1929.4779052734375, 325.6138916015625, 1685.6307373046875],
				"FlickerAmp:f":	15,
				"FlickerJitter:f":	5,
				"FlickerSpeed:f":	10,
				"AttenStart:f":	0,
				"AttenEnd:f":	1000,
				"Dynamic:d":	0,
				"Flicker:d":	0,
				"TargetAttr:d":	7248,
				"LightChannel:d":	1
			}]
	}, {
		"name":	"Light",
		"row_count":	1,
		"rows":	[{
				"GUID:s":	"B5D7A0C9_3D2E2400",
				"Name:s":	"ent_Point_50",
				"Kind:d":	1,
				"Color:dddd":	[7, 250, 255, 255],
				"Intensity:f":	2,
				"Pos:fff":	[1528.249267578125, 981.8594970703125, 3855.339111328125],
				"FlickerAmp:f":	15,
				"FlickerJitter:f":	5,
				"FlickerSpeed:f":	10,
				"AttenStart:f":	0,
				"AttenEnd:f":	580,
				"Dynamic:d":	0,
				"Flicker:d":	0,
				"TargetAttr:d":	7248,
				"LightChannel:d":	1
			}]
	}, {
		"name":	"Light",
		"row_count":	1,
		"rows":	[{
				"GUID:s":	"B5D7A0C9_3D2F9C01",
				"Name:s":	"ent_Point_51",
				"Kind:d":	1,
				"Color:dddd":	[255, 197, 7, 255],
				"Intensity:f":	2,
				"Pos:fff":	[94.6147232055664, 1184.537109375, 4580.318359375],
				"FlickerAmp:f":	15,
				"FlickerJitter:f":	5,
				"FlickerSpeed:f":	10,
				"AttenStart:f":	0,
				"AttenEnd:f":	400,
				"Dynamic:d":	0,
				"Flicker:d":	0,
				"TargetAttr:d":	7248,
				"LightChannel:d":	1
			}]
	}, {
		"name":	"Light",
		"row_count":	1,
		"rows":	[{
				"GUID:s":	"B5D7A0C9_3D30B401",
				"Name:s":	"ent_Point_52",
				"Kind:d":	1,
				"Color:dddd":	[7, 255, 238, 255],
				"Intensity:f":	1.6000000238418579,
				"Pos:fff":	[602.751953125, 1210.3935546875, 4743.6591796875],
				"FlickerAmp:f":	15,
				"FlickerJitter:f":	5,
				"FlickerSpeed:f":	10,
				"AttenStart:f":	0,
				"AttenEnd:f":	650,
				"Dynamic:d":	0,
				"Flicker:d":	0,
				"TargetAttr:d":	7248,
				"LightChannel:d":	1
			}]
	}, {
		"name":	"Light",
		"row_count":	1,
		"rows":	[{
				"GUID:s":	"B5D7A0C9_3D31AC01",
				"Name:s":	"ent_Point_53",
				"Kind:d":	1,
				"Color:dddd":	[7, 255, 238, 255],
				"Intensity:f":	1,
				"Pos:fff":	[350.46652221679687, 1210.393798828125, 5262.3515625],
				"FlickerAmp:f":	15,
				"FlickerJitter:f":	5,
				"FlickerSpeed:f":	10,
				"AttenStart:f":	0,
				"AttenEnd:f":	600,
				"Dynamic:d":	0,
				"Flicker:d":	0,
				"TargetAttr:d":	7248,
				"LightChannel:d":	1
			}]
	}, {
		"name":	"Light",
		"row_count":	1,
		"rows":	[{
				"GUID:s":	"B5D7A0C9_3D332401",
				"Name:s":	"ent_Point_54",
				"Kind:d":	1,
				"Color:dddd":	[7, 255, 238, 255],
				"Intensity:f":	1.6000000238418579,
				"Pos:fff":	[-408.49713134765625, 1210.393798828125, 5384.82666015625],
				"FlickerAmp:f":	15,
				"FlickerJitter:f":	5,
				"FlickerSpeed:f":	10,
				"AttenStart:f":	0,
				"AttenEnd:f":	350,
				"Dynamic:d":	0,
				"Flicker:d":	0,
				"TargetAttr:d":	7248,
				"LightChannel:d":	1
			}]
	}, {
		"name":	"Light",
		"row_count":	1,
		"rows":	[{
				"GUID:s":	"B5D7A0C9_3D342001",
				"Name:s":	"ent_Point_55",
				"Kind:d":	1,
				"Color:dddd":	[7, 255, 238, 255],
				"Intensity:f":	1.6000000238418579,
				"Pos:fff":	[-324.39019775390625, 785.805908203125, 4871.42333984375],
				"FlickerAmp:f":	15,
				"FlickerJitter:f":	5,
				"FlickerSpeed:f":	10,
				"AttenStart:f":	0,
				"AttenEnd:f":	500,
				"Dynamic:d":	0,
				"Flicker:d":	0,
				"TargetAttr:d":	7248,
				"LightChannel:d":	1
			}]
	}, {
		"name":	"Light",
		"row_count":	1,
		"rows":	[{
				"GUID:s":	"B5D7AA49_3C5E6801",
				"Name:s":	"ent_Point_6",
				"Kind:d":	1,
				"Color:dddd":	[220, 163, 15, 255],
				"Intensity:f":	1.2999999523162842,
				"Pos:fff":	[-1482.9407958984375, 325.61358642578125, 1721.8912353515625],
				"FlickerAmp:f":	15,
				"FlickerJitter:f":	5,
				"FlickerSpeed:f":	10,
				"AttenStart:f":	0,
				"AttenEnd:f":	1000,
				"Dynamic:d":	0,
				"Flicker:d":	0,
				"TargetAttr:d":	7248,
				"LightChannel:d":	1
			}]
	}, {
		"name":	"Light",
		"row_count":	1,
		"rows":	[{
				"GUID:s":	"B5D7AA49_3C5F0C01",
				"Name:s":	"ent_Point_7",
				"Kind:d":	1,
				"Color:dddd":	[255, 163, 15, 255],
				"Intensity:f":	1.5,
				"Pos:fff":	[-1864.4569091796875, 385.0897216796875, 2345.90771484375],
				"FlickerAmp:f":	15,
				"FlickerJitter:f":	5,
				"FlickerSpeed:f":	10,
				"AttenStart:f":	0,
				"AttenEnd:f":	1300,
				"Dynamic:d":	0,
				"Flicker:d":	0,
				"TargetAttr:d":	7248,
				"LightChannel:d":	1
			}]
	}, {
		"name":	"Light",
		"row_count":	1,
		"rows":	[{
				"GUID:s":	"B5D7AA49_3C5FE801",
				"Name:s":	"ent_Point_8",
				"Kind:d":	1,
				"Color:dddd":	[220, 163, 15, 255],
				"Intensity:f":	1.5,
				"Pos:fff":	[-2471.369873046875, 930.1151123046875, 4101.91748046875],
				"FlickerAmp:f":	15,
				"FlickerJitter:f":	5,
				"FlickerSpeed:f":	10,
				"AttenStart:f":	0,
				"AttenEnd:f":	1400,
				"Dynamic:d":	0,
				"Flicker:d":	0,
				"TargetAttr:d":	7248,
				"LightChannel:d":	1
			}]
	}, {
		"name":	"Light",
		"row_count":	1,
		"rows":	[{
				"GUID:s":	"B5D7A509_3C693401",
				"Name:s":	"ent_Point_9",
				"Kind:d":	1,
				"Color:dddd":	[220, 163, 15, 255],
				"Intensity:f":	1.5,
				"Pos:fff":	[-1404.3612060546875, 930.114013671875, 5092.69287109375],
				"FlickerAmp:f":	15,
				"FlickerJitter:f":	5,
				"FlickerSpeed:f":	10,
				"AttenStart:f":	0,
				"AttenEnd:f":	1300,
				"Dynamic:d":	0,
				"Flicker:d":	0,
				"TargetAttr:d":	7248,
				"LightChannel:d":	1
			}]
	}]